Workbook

Sheet Portada
B2: CONCILIACION DE VENTAS 2026 - EXCEL MAESTRO
B3: Fuente unica de verdad construida a partir de la carpeta 'reportes de ventas'
B5: Generado | C5: 06/09/2026
B6: Periodo cubierto | C6: Enero a Mayo 2026
B7: Operaciones conciliadas | C7: 886
B8: Archivos fuente procesados | C8: 7 fuentes transaccionales y 6 catalogos
B9: Fecha de corte para cobranza | C9: 31/05/2026 (supuesto: cierre del periodo analizado)
B11: COMO LEER ESTE ARCHIVO
B12: Resumen Ejecutivo | C12: KPIs del periodo, todos con formula viva
B13: Datos | C13: Las 886 operaciones normalizadas. Cada fila dice de que archivo, hoja y fila salio
B14: Analisis | C14: Cortes por mes, sucursal, vendedor y producto. Todo con SUMAR.SI.CONJUNTO contra Datos
B15: Cobranza | C15: Cartera consolidada de los dos archivos de cobranza, con antiguedad
B16: Cat_Productos / Cat_Vendedores / Cat_Gastos / Cat_Clientes | C16: Catalogos de apoyo que alimentan las formulas
B17: Diccionario | C17: Cada variante de nombre que se agrupo y bajo que criterio
B18: Conciliacion | C18: Bitacora de cada decision tomada sobre los datos
B19: Excepciones | C19: Todo lo que quedo sospechoso o incompleto, ordenado por impacto
B20: Validacion | C20: Comparacion contra los reportes que ya existian en la carpeta
B22: REGLA DE ORO | C22: Si editas la hoja Datos, todo lo demas se recalcula solo. No hay valores pegados en los analisis
B23: CELDAS EN AMBAR | C23: Importes que el maestro calculo o corrigio. Estan listadas en Excepciones

Sheet Resumen Ejecutivo
B2: RESUMEN EJECUTIVO
B3: Enero a mayo 2026 | 886 operaciones conciliadas de 7 archivos de origen
B5: Venta total del periodo | C5: =Analisis!B11 -> 13235390 | D5: Suma de las 886 operaciones del maestro
B6: Operaciones | C6: =Analisis!C11 -> 886 | D6: Numero de lineas de venta conciliadas
B7: Unidades vendidas | C7: =Analisis!D11 -> 3272
B8: Ticket promedio | C8: =IFERROR(C5/C6,0) -> 14938.363 | D8: Venta total entre operaciones
B9: Margen bruto | C9: =Analisis!F11 -> 3673140 | D9: Venta menos costo de catalogo. No incluye gastos
B10: % Margen bruto | C10: =IFERROR(C9/C5,0) -> 0.27752412
B11: Gastos operativos del periodo | C11: =SUM(Cat_Gastos!$G$2:$G$16) -> 3388145 | D11: Renta, nomina, servicios y otros de las tres sucursales
B12: Utilidad estimada | C12: =C9-C11 -> 284995 | D12: Margen bruto menos gastos operativos
B13: Ventas de mayo | C13: =Analisis!B10 -> 2848860
B14: Crecimiento mayo vs abril | C14: =Analisis!H10 -> -0.076044407 | D14: Mayo tiene 120 operaciones contra 187 de abril
B15: Cumplimiento de meta en mayo | C15: =IFERROR(Analisis!F29/Analisis!G29,0) -> 1.8866623 | D15: Ventas de mayo entre la suma de metas mensuales
B16: Comisiones por pagar de mayo | C16: =Analisis!J29 -> 115009.75 | D16: Calculadas con el porcentaje del catalogo comercial
B17: Cartera total | C17: =Analisis!C51 -> 1813900 | D17: Facturas de los dos archivos de cobranza, sin duplicar
B18: Cartera vencida | C18: =SUM(Analisis!C46:C49) -> 446100 | D18: Facturas con mas de un dia de atraso al 31/05/2026
B19: % Cartera vencida sobre la cartera | C19: =IFERROR(C18/C17,0) -> 0.24593417
B20: Filas excluidas del maestro | C20: 5 | D20: Sin fecha legible. Estan listadas en Excepciones
B21: Diferencia contra los reportes previos | C21: =SUM(Validacion!E4:E10) -> -1500 | D21: Suma de las diferencias explicadas en la hoja Validacion
B23: LO QUE HAY QUE ARREGLAR
B24: 1. La captura de ventas vive en 7 archivos con 4 formatos de fecha y 53 variantes de nombre. Un solo formulario o plantilla unica elimina el 90% del trabajo de conciliacion.
B25: 2. Faltan capturas: 28 al 30 de abril (Ana), notas de marzo de Luis y 4,720 de Juan Perez en mayo. El hueco se arrastra desde julio sin resolverse.
B26: 3. Ana Torres cae 40% en mayo (de 776,720 a 466,010) y es la unica caida fuerte del equipo. Hay que confirmar si es captura pendiente o caida real de venta.
B27: 4. El precio de lista de abril del Monitor 27 dice 6,300 y se facturo a 6,200 en 13 operaciones. Hay que decidir cual es el precio bueno.
B28: 5. La devolucion de marzo por 24,500 sigue capturada en positivo. Definir si se resta de la venta o se registra aparte.

Sheet Analisis
A1: ANALISIS DEL PERIODO
A2: Todo se calcula con formulas contra la hoja Datos. Si Datos cambia, esto cambia.
A4: 1. VENTAS POR MES
A5: Mes | B5: Ventas | C5: Operaciones | D5: Unidades | E5: Ticket promedio | F5: Margen bruto | G5: % Margen | H5: Var. vs mes anterior
A6: Enero | B6: =SUMIFS(Datos!$J$2:$J$887,Datos!$D$2:$D$887,$A6) -> 2137680 | C6: =COUNTIFS(Datos!$D$2:$D$887,$A6) -> 181 | D6: =SUMIFS(Datos!$H$2:$H$887,Datos!$D$2:$D$887,$A6) -> 688 | E6: =IFERROR(B6/C6,0) -> 11810.387 | F6: =SUMIFS(Datos!$N$2:$N$887,Datos!$D$2:$D$887,$A6) -> 609920 | G6: =IFERROR(F6/B6,0) -> 0.28531866
A7: Febrero | B7: =SUMIFS(Datos!$J$2:$J$887,Datos!$D$2:$D$887,$A7) -> 2415260 | C7: =COUNTIFS(Datos!$D$2:$D$887,$A7) -> 174 | D7: =SUMIFS(Datos!$H$2:$H$887,Datos!$D$2:$D$887,$A7) -> 630 | E7: =IFERROR(B7/C7,0) -> 13880.805 | F7: =SUMIFS(Datos!$N$2:$N$887,Datos!$D$2:$D$887,$A7) -> 648100 | G7: =IFERROR(F7/B7,0) -> 0.2683355 | H7: =IFERROR(B7/B6-1,0) -> 0.12985105
A8: Marzo | B8: =SUMIFS(Datos!$J$2:$J$887,Datos!$D$2:$D$887,$A8) -> 2750260 | C8: =COUNTIFS(Datos!$D$2:$D$887,$A8) -> 224 | D8: =SUMIFS(Datos!$H$2:$H$887,Datos!$D$2:$D$887,$A8) -> 863 | E8: =IFERROR(B8/C8,0) -> 12277.946 | F8: =SUMIFS(Datos!$N$2:$N$887,Datos!$D$2:$D$887,$A8) -> 812060 | G8: =IFERROR(F8/B8,0) -> 0.29526663 | H8: =IFERROR(B8/B7-1,0) -> 0.13870142
A9: Abril | B9: =SUMIFS(Datos!$J$2:$J$887,Datos!$D$2:$D$887,$A9) -> 3083330 | C9: =COUNTIFS(Datos!$D$2:$D$887,$A9) -> 187 | D9: =SUMIFS(Datos!$H$2:$H$887,Datos!$D$2:$D$887,$A9) -> 679 | E9: =IFERROR(B9/C9,0) -> 16488.396 | F9: =SUMIFS(Datos!$N$2:$N$887,Datos!$D$2:$D$887,$A9) -> 855180 | G9: =IFERROR(F9/B9,0) -> 0.27735598 | H9: =IFERROR(B9/B8-1,0) -> 0.12110491
A10: Mayo | B10: =SUMIFS(Datos!$J$2:$J$887,Datos!$D$2:$D$887,$A10) -> 2848860 | C10: =COUNTIFS(Datos!$D$2:$D$887,$A10) -> 120 | D10: =SUMIFS(Datos!$H$2:$H$887,Datos!$D$2:$D$887,$A10) -> 412 | E10: =IFERROR(B10/C10,0) -> 23740.5 | F10: =SUMIFS(Datos!$N$2:$N$887,Datos!$D$2:$D$887,$A10) -> 747880 | G10: =IFERROR(F10/B10,0) -> 0.26251904 | H10: =IFERROR(B10/B9-1,0) -> -0.076044407
A11: TOTAL | B11: =SUM(B6:B10) -> 13235390 | C11: =SUM(C6:C10) -> 886 | D11: =SUM(D6:D10) -> 3272 | E11: =IFERROR(B11/C11,0) -> 14938.363 | F11: =SUM(F6:F10) -> 3673140 | G11: =IFERROR(F11/B11,0) -> 0.27752412
A13: 2. VENTAS POR SUCURSAL
A14: Sucursal | B14: Enero | C14: Febrero | D14: Marzo | E14: Abril | F14: Mayo | G14: Total periodo | H14: Gastos del periodo | I14: Margen bruto | J14: Utilidad estimada | K14: % Utilidad
A15: CDMX | B15: =SUMIFS(Datos!$J$2:$J$887,Datos!$E$2:$E$887,$A15,Datos!$D$2:$D$887,B$14) -> 993780 | C15: =SUMIFS(Datos!$J$2:$J$887,Datos!$E$2:$E$887,$A15,Datos!$D$2:$D$887,C$14) -> 1109870 | D15: =SUMIFS(Datos!$J$2:$J$887,Datos!$E$2:$E$887,$A15,Datos!$D$2:$D$887,D$14) -> 1165650 | E15: =SUMIFS(Datos!$J$2:$J$887,Datos!$E$2:$E$887,$A15,Datos!$D$2:$D$887,E$14) -> 1283740 | F15: =SUMIFS(Datos!$J$2:$J$887,Datos!$E$2:$E$887,$A15,Datos!$D$2:$D$887,F$14) -> 1106280 | G15: =SUM(B15:F15) -> 5659320 | H15: =SUMIFS(Cat_Gastos!$G$2:$G$16,Cat_Gastos!$A$2:$A$16,$A15) -> 1346032 | I15: =SUMIFS(Datos!$N$2:$N$887,Datos!$E$2:$E$887,$A15) -> 1608930 | J15: =I15-H15 -> 262898 | K15: =IFERROR(J15/G15,0) -> 0.046453991
A16: Guadalajara | B16: =SUMIFS(Datos!$J$2:$J$887,Datos!$E$2:$E$887,$A16,Datos!$D$2:$D$887,B$14) -> 523980 | C16: =SUMIFS(Datos!$J$2:$J$887,Datos!$E$2:$E$887,$A16,Datos!$D$2:$D$887,C$14) -> 603960 | D16: =SUMIFS(Datos!$J$2:$J$887,Datos!$E$2:$E$887,$A16,Datos!$D$2:$D$887,D$14) -> 840050 | E16: =SUMIFS(Datos!$J$2:$J$887,Datos!$E$2:$E$887,$A16,Datos!$D$2:$D$887,E$14) -> 994610 | F16: =SUMIFS(Datos!$J$2:$J$887,Datos!$E$2:$E$887,$A16,Datos!$D$2:$D$887,F$14) -> 1265400 | G16: =SUM(B16:F16) -> 4228000 | H16: =SUMIFS(Cat_Gastos!$G$2:$G$16,Cat_Gastos!$A$2:$A$16,$A16) -> 1097067 | I16: =SUMIFS(Datos!$N$2:$N$887,Datos!$E$2:$E$887,$A16) -> 1133140 | J16: =I16-H16 -> 36073 | K16: =IFERROR(J16/G16,0) -> 0.00853193
A17: Monterrey | B17: =SUMIFS(Datos!$J$2:$J$887,Datos!$E$2:$E$887,$A17,Datos!$D$2:$D$887,B$14) -> 619920 | C17: =SUMIFS(Datos!$J$2:$J$887,Datos!$E$2:$E$887,$A17,Datos!$D$2:$D$887,C$14) -> 701430 | D17: =SUMIFS(Datos!$J$2:$J$887,Datos!$E$2:$E$887,$A17,Datos!$D$2:$D$887,D$14) -> 744560 | E17: =SUMIFS(Datos!$J$2:$J$887,Datos!$E$2:$E$887,$A17,Datos!$D$2:$D$887,E$14) -> 804980 | F17: =SUMIFS(Datos!$J$2:$J$887,Datos!$E$2:$E$887,$A17,Datos!$D$2:$D$887,F$14) -> 477180 | G17: =SUM(B17:F17) -> 3348070 | H17: =SUMIFS(Cat_Gastos!$G$2:$G$16,Cat_Gastos!$A$2:$A$16,$A17) -> 945046 | I17: =SUMIFS(Datos!$N$2:$N$887,Datos!$E$2:$E$887,$A17) -> 931070 | J17: =I17-H17 -> -13976 | K17: =IFERROR(J17/G17,0) -> -0.0041743452
A18: TOTAL | B18: =SUM(B15:B17) -> 2137680 | C18: =SUM(C15:C17) -> 2415260 | D18: =SUM(D15:D17) -> 2750260 | E18: =SUM(E15:E17) -> 3083330 | F18: =SUM(F15:F17) -> 2848860 | G18: =SUM(G15:G17) -> 13235390 | H18: =SUM(H15:H17) -> 3388145 | I18: =SUM(I15:I17) -> 3673140 | J18: =SUM(J15:J17) -> 284995 | K18: =IFERROR(J18/G18,0) -> 0.0215328
A19: Nota: los gastos del catalogo cubren enero a mayo. La utilidad estimada no incluye gastos corporativos.
A21: 3. DESEMPENO POR VENDEDOR
A22: Vendedor | B22: Sucursal | C22: Ventas Ene-May | D22: Operaciones | E22: Ticket promedio | F22: Ventas Mayo | G22: Meta mensual | H22: Cumplimiento Mayo | I22: % Comision | J22: Comision Mayo
A23: Ana Torres | B23: =IFERROR(INDEX(Cat_Vendedores!$B$2:$B$7,MATCH($A23,Cat_Vendedores!$A$2:$A$7,0)),"sin catalogo") -> CDMX | C23: =SUMIFS(Datos!$J$2:$J$887,Datos!$F$2:$F$887,$A23) -> 3208210 | D23: =COUNTIFS(Datos!$F$2:$F$887,$A23) -> 235 | E23: =IFERROR(C23/D23,0) -> 13651.957 | F23: =SUMIFS(Datos!$J$2:$J$887,Datos!$F$2:$F$887,$A23,Datos!$D$2:$D$887,"Mayo") -> 466010 | G23: =IFERROR(INDEX(Cat_Vendedores!$C$2:$C$7,MATCH($A23,Cat_Vendedores!$A$2:$A$7,0)),0) -> 220000 | H23: =IFERROR(F23/G23,0) -> 2.1182273 | I23: =IFERROR(INDEX(Cat_Vendedores!$D$2:$D$7,MATCH($A23,Cat_Vendedores!$A$2:$A$7,0)),0) -> 0.025 | J23: =F23*I23 -> 11650.25
A24: Carlos Ruiz | B24: =IFERROR(INDEX(Cat_Vendedores!$B$2:$B$7,MATCH($A24,Cat_Vendedores!$A$2:$A$7,0)),"sin catalogo") -> Monterrey | C24: =SUMIFS(Datos!$J$2:$J$887,Datos!$F$2:$F$887,$A24) -> 1157070 | D24: =COUNTIFS(Datos!$F$2:$F$887,$A24) -> 101 | E24: =IFERROR(C24/D24,0) -> 11456.139 | F24: =SUMIFS(Datos!$J$2:$J$887,Datos!$F$2:$F$887,$A24,Datos!$D$2:$D$887,"Mayo") -> 242980 | G24: =IFERROR(INDEX(Cat_Vendedores!$C$2:$C$7,MATCH($A24,Cat_Vendedores!$A$2:$A$7,0)),0) -> 280000 | H24: =IFERROR(F24/G24,0) -> 0.86778571 | I24: =IFERROR(INDEX(Cat_Vendedores!$D$2:$D$7,MATCH($A24,Cat_Vendedores!$A$2:$A$7,0)),0) -> 0.045 | J24: =F24*I24 -> 10934.1
A25: Juan Pérez | B25: =IFERROR(INDEX(Cat_Vendedores!$B$2:$B$7,MATCH($A25,Cat_Vendedores!$A$2:$A$7,0)),"sin catalogo") -> Guadalajara | C25: =SUMIFS(Datos!$J$2:$J$887,Datos!$F$2:$F$887,$A25) -> 3288480 | D25: =COUNTIFS(Datos!$F$2:$F$887,$A25) -> 191 | E25: =IFERROR(C25/D25,0) -> 17217.173 | F25: =SUMIFS(Datos!$J$2:$J$887,Datos!$F$2:$F$887,$A25,Datos!$D$2:$D$887,"Mayo") -> 706430 | G25: =IFERROR(INDEX(Cat_Vendedores!$C$2:$C$7,MATCH($A25,Cat_Vendedores!$A$2:$A$7,0)),0) -> 250000 | H25: =IFERROR(F25/G25,0) -> 2.82572 | I25: =IFERROR(INDEX(Cat_Vendedores!$D$2:$D$7,MATCH($A25,Cat_Vendedores!$A$2:$A$7,0)),0) -> 0.03 | J25: =F25*I25 -> 21192.9
A26: Luis Gómez | B26: =IFERROR(INDEX(Cat_Vendedores!$B$2:$B$7,MATCH($A26,Cat_Vendedores!$A$2:$A$7,0)),"sin catalogo") -> Guadalajara | C26: =SUMIFS(Datos!$J$2:$J$887,Datos!$F$2:$F$887,$A26) -> 767170 | D26: =COUNTIFS(Datos!$F$2:$F$887,$A26) -> 52 | E26: =IFERROR(C26/D26,0) -> 14753.269 | F26: =SUMIFS(Datos!$J$2:$J$887,Datos!$F$2:$F$887,$A26,Datos!$D$2:$D$887,"Mayo") -> 384260 | G26: =IFERROR(INDEX(Cat_Vendedores!$C$2:$C$7,MATCH($A26,Cat_Vendedores!$A$2:$A$7,0)),0) -> 260000 | H26: =IFERROR(F26/G26,0) -> 1.4779231 | I26: =IFERROR(INDEX(Cat_Vendedores!$D$2:$D$7,MATCH($A26,Cat_Vendedores!$A$2:$A$7,0)),0) -> 0.035 | J26: =F26*I26 -> 13449.1
A27: María López | B27: =IFERROR(INDEX(Cat_Vendedores!$B$2:$B$7,MATCH($A27,Cat_Vendedores!$A$2:$A$7,0)),"sin catalogo") -> CDMX | C27: =SUMIFS(Datos!$J$2:$J$887,Datos!$F$2:$F$887,$A27) -> 2327580 | D27: =COUNTIFS(Datos!$F$2:$F$887,$A27) -> 167 | E27: =IFERROR(C27/D27,0) -> 13937.605 | F27: =SUMIFS(Datos!$J$2:$J$887,Datos!$F$2:$F$887,$A27,Datos!$D$2:$D$887,"Mayo") -> 516740 | G27: =IFERROR(INDEX(Cat_Vendedores!$C$2:$C$7,MATCH($A27,Cat_Vendedores!$A$2:$A$7,0)),0) -> 300000 | H27: =IFERROR(F27/G27,0) -> 1.7224667 | I27: =IFERROR(INDEX(Cat_Vendedores!$D$2:$D$7,MATCH($A27,Cat_Vendedores!$A$2:$A$7,0)),0) -> 0.05 | J27: =F27*I27 -> 25837
A28: Sofía Martínez | B28: =IFERROR(INDEX(Cat_Vendedores!$B$2:$B$7,MATCH($A28,Cat_Vendedores!$A$2:$A$7,0)),"sin catalogo") -> Monterrey | C28: =SUMIFS(Datos!$J$2:$J$887,Datos!$F$2:$F$887,$A28) -> 2486880 | D28: =COUNTIFS(Datos!$F$2:$F$887,$A28) -> 140 | E28: =IFERROR(C28/D28,0) -> 17763.429 | F28: =SUMIFS(Datos!$J$2:$J$887,Datos!$F$2:$F$887,$A28,Datos!$D$2:$D$887,"Mayo") -> 532440 | G28: =IFERROR(INDEX(Cat_Vendedores!$C$2:$C$7,MATCH($A28,Cat_Vendedores!$A$2:$A$7,0)),0) -> 200000 | H28: =IFERROR(F28/G28,0) -> 2.6622 | I28: =IFERROR(INDEX(Cat_Vendedores!$D$2:$D$7,MATCH($A28,Cat_Vendedores!$A$2:$A$7,0)),0) -> 0.06 | J28: =F28*I28 -> 31946.4
A29: TOTAL | C29: =SUM(C23:C28) -> 13235390 | D29: =SUM(D23:D28) -> 886 | E29: =IFERROR(C29/D29,0) -> 14938.363 | F29: =SUM(F23:F28) -> 2848860 | G29: =SUM(G23:G28) -> 1510000 | H29: =IFERROR(F29/G29,0) -> 1.8866623 | J29: =SUM(J23:J28) -> 115009.75
A30: Nota: Luis Gomez empezo a vender en marzo. Sus meses vacios de enero y febrero no son un hueco de conciliacion, es su fecha de ingreso.
A32: 4. VENTAS POR PRODUCTO
A33: Producto | B33: Unidades | C33: Ventas | D33: Costo total | E33: Margen bruto | F33: % Margen | G33: % de la venta total
A34: Laptop Pro 14 | B34: =SUMIFS(Datos!$H$2:$H$887,Datos!$G$2:$G$887,$A34) -> 391 | C34: =SUMIFS(Datos!$J$2:$J$887,Datos!$G$2:$G$887,$A34) -> 9503500 | D34: =SUMIFS(Datos!$M$2:$M$887,Datos!$G$2:$G$887,$A34) -> 7507200 | E34: =C34-D34 -> 1996300 | F34: =IFERROR(E34/C34,0) -> 0.21005945 | G34: =IFERROR(C34/$B$11,0) -> 0.71803702
A35: Monitor 27" | B35: =SUMIFS(Datos!$H$2:$H$887,Datos!$G$2:$G$887,$A35) -> 141 | C35: =SUMIFS(Datos!$J$2:$J$887,Datos!$G$2:$G$887,$A35) -> 868500 | D35: =SUMIFS(Datos!$M$2:$M$887,Datos!$G$2:$G$887,$A35) -> 578100 | E35: =C35-D35 -> 290400 | F35: =IFERROR(E35/C35,0) -> 0.3343696 | G35: =IFERROR(C35/$B$11,0) -> 0.065619525
A36: Mouse Inalámbrico | B36: =SUMIFS(Datos!$H$2:$H$887,Datos!$G$2:$G$887,$A36) -> 1273 | C36: =SUMIFS(Datos!$J$2:$J$887,Datos!$G$2:$G$887,$A36) -> 789260 | D36: =SUMIFS(Datos!$M$2:$M$887,Datos!$G$2:$G$887,$A36) -> 369170 | E36: =C36-D36 -> 420090 | F36: =IFERROR(E36/C36,0) -> 0.53225806 | G36: =IFERROR(C36/$B$11,0) -> 0.059632546
A37: Teclado Mecánico | B37: =SUMIFS(Datos!$H$2:$H$887,Datos!$G$2:$G$887,$A37) -> 1275 | C37: =SUMIFS(Datos!$J$2:$J$887,Datos!$G$2:$G$887,$A37) -> 1847570 | D37: =SUMIFS(Datos!$M$2:$M$887,Datos!$G$2:$G$887,$A37) -> 994500 | E37: =C37-D37 -> 853070 | F37: =IFERROR(E37/C37,0) -> 0.4617254 | G37: =IFERROR(C37/$B$11,0) -> 0.13959317
A38: Webcam HD | B38: =SUMIFS(Datos!$H$2:$H$887,Datos!$G$2:$G$887,$A38) -> 192 | C38: =SUMIFS(Datos!$J$2:$J$887,Datos!$G$2:$G$887,$A38) -> 226560 | D38: =SUMIFS(Datos!$M$2:$M$887,Datos!$G$2:$G$887,$A38) -> 113280 | E38: =C38-D38 -> 113280 | F38: =IFERROR(E38/C38,0) -> 0.5 | G38: =IFERROR(C38/$B$11,0) -> 0.017117743
A39: TOTAL | B39: =SUM(B34:B38) -> 3272 | C39: =SUM(C34:C38) -> 13235390 | D39: =SUM(D34:D38) -> 9562250 | E39: =SUM(E34:E38) -> 3673140 | F39: =IFERROR(E39/C39,0) -> 0.27752412 | G39: =IFERROR(C39/$B$11,0) -> 1
A42: 5. CARTERA POR ANTIGUEDAD
A43: Antiguedad | B43: Facturas | C43: Monto | D43: % de la cartera
A44: Pagado | B44: =COUNTIFS(Cobranza!$I$4:$I$57,$A44) -> 29 | C44: =SUMIFS(Cobranza!$F$4:$F$57,Cobranza!$I$4:$I$57,$A44) -> 991100 | D44: =IFERROR(C44/$C$51,0) -> 0.54639175
A45: Por vencer | B45: =COUNTIFS(Cobranza!$I$4:$I$57,$A45) -> 7 | C45: =SUMIFS(Cobranza!$F$4:$F$57,Cobranza!$I$4:$I$57,$A45) -> 210300 | D45: =IFERROR(C45/$C$51,0) -> 0.11593803
A46: 1 a 30 dias | B46: =COUNTIFS(Cobranza!$I$4:$I$57,$A46) -> 5 | C46: =SUMIFS(Cobranza!$F$4:$F$57,Cobranza!$I$4:$I$57,$A46) -> 131200 | D46: =IFERROR(C46/$C$51,0) -> 0.072330338
A47: 31 a 60 dias | B47: =COUNTIFS(Cobranza!$I$4:$I$57,$A47) -> 7 | C47: =SUMIFS(Cobranza!$F$4:$F$57,Cobranza!$I$4:$I$57,$A47) -> 314900 | D47: =IFERROR(C47/$C$51,0) -> 0.17360384
A48: 61 a 90 dias | B48: =COUNTIFS(Cobranza!$I$4:$I$57,$A48) -> 0 | C48: =SUMIFS(Cobranza!$F$4:$F$57,Cobranza!$I$4:$I$57,$A48) -> 0 | D48: =IFERROR(C48/$C$51,0) -> 0
A49: Mas de 90 dias | B49: =COUNTIFS(Cobranza!$I$4:$I$57,$A49) -> 0 | C49: =SUMIFS(Cobranza!$F$4:$F$57,Cobranza!$I$4:$I$57,$A49) -> 0 | D49: =IFERROR(C49/$C$51,0) -> 0
A50: Sin fecha de vencimiento | B50: =COUNTIFS(Cobranza!$I$4:$I$57,$A50) -> 6 | C50: =SUMIFS(Cobranza!$F$4:$F$57,Cobranza!$I$4:$I$57,$A50) -> 166400 | D50: =IFERROR(C50/$C$51,0) -> 0.091736038
A51: TOTAL CARTERA | B51: =SUM(B44:B50) -> 54 | C51: =SUM(C44:C50) -> 1813900

Sheet Datos
A1: Fecha | B1: Anio | C1: Mes | D1: Mes_Nombre | E1: Sucursal | F1: Vendedor | G1: Producto | H1: Cantidad | I1: Precio_Unitario | J1: Importe | K1: Importe_Calculado | L1: Costo_Unitario | M1: Costo_Total | N1: Margen | O1: Margen_% | P1: Obs_Origen | Q1: Archivo_Origen | R1: Hoja_Origen | S1: Fila_Origen | T1: Banderas
A2: 46023 | B2: 2026 | C2: 1 | D2: Enero | E2: Monterrey | F2: Sofía Martínez | G2: Teclado Mecánico | H2: 2 | I2: 1450 | J2: 2900 | K2: =H2*I2 -> 2900 | L2: =IFERROR(INDEX(Cat_Productos!$B$2:$B$6,MATCH(G2,Cat_Productos!$A$2:$A$6,0)),"") -> 780 | M2: =IF(L2="","",H2*L2) -> 1560 | N2: =IF(M2="","",J2-M2) -> 1340 | O2: =IFERROR(N2/J2,0) -> 0.46206897 | Q2: ventas enero FINAL FINAL.xlsx | R2: enero | S2: 58
A3: 46023 | B3: 2026 | C3: 1 | D3: Enero | E3: Monterrey | F3: Carlos Ruiz | G3: Teclado Mecánico | H3: 2 | I3: 1450 | J3: 2900 | K3: =H3*I3 -> 2900 | L3: =IFERROR(INDEX(Cat_Productos!$B$2:$B$6,MATCH(G3,Cat_Productos!$A$2:$A$6,0)),"") -> 780 | M3: =IF(L3="","",H3*L3) -> 1560 | N3: =IF(M3="","",J3-M3) -> 1340 | O3: =IFERROR(N3/J3,0) -> 0.46206897 | Q3: ventas enero FINAL FINAL.xlsx | R3: enero | S3: 165
A4: 46023 | B4: 2026 | C4: 1 | D4: Enero | E4: CDMX | F4: Ana Torres | G4: Teclado Mecánico | H4: 4 | I4: 1450 | J4: 5800 | K4: =H4*I4 -> 5800 | L4: =IFERROR(INDEX(Cat_Productos!$B$2:$B$6,MATCH(G4,Cat_Productos!$A$2:$A$6,0)),"") -> 780 | M4: =IF(L4="","",H4*L4) -> 3120 | N4: =IF(M4="","",J4-M4) -> 2680 | O4: =IFERROR(N4/J4,0) -> 0.46206897 | Q4: ventas enero FINAL FINAL.xlsx | R4: enero | S4: 120
A5: 46023 | B5: 2026 | C5: 1 | D5: Enero | E5: Monterrey | F5: Carlos Ruiz | G5: Mouse Inalámbrico | H5: 2 | I5: 620 | J5: 1240 | K5: =H5*I5 -> 1240 | L5: =IFERROR(INDEX(Cat_Productos!$B$2:$B$6,MATCH(G5,Cat_Productos!$A$2:$A$6,0)),"") -> 290 | M5: =IF(L5="","",H5*L5) -> 580 | N5: =IF(M5="","",J5-M5) -> 660 | O5: =IFERROR(N5/J5,0) -> 0.53225806 | Q5: ventas enero FINAL FINAL.xlsx | R5: enero | S5: 177
A6: 46023 | B6: 2026 | C6: 1 | D6: Enero | E6: Guadalajara | F6: Juan Pérez | G6: Mouse Inalámbrico | H6: 6 | I6: 620 | J6: 3720 | K6: =H6*I6 -> 3720 | L6: =IFERROR(INDEX(Cat_Productos!$B$2:$B$6,MATCH(G6,Cat_Productos!$A$2:$A$6,0)),"") -> 290 | M6: =IF(L6="","",H6*L6) -> 1740 | N6: =IF(M6="","",J6-M6) -> 1980 | O6: =IFERROR(N6/J6,0) -> 0.53225806 | Q6: ventas enero FINAL FINAL.xlsx | R6: enero | S6: 38
A7: 46023 | B7: 2026 | C7: 1 | D7: Enero | E7: Monterrey | F7: Carlos Ruiz | G7: Mouse Inalámbrico | H7: 2 | I7: 620 | J7: 1240 | K7: =H7*I7 -> 1240 | L7: =IFERROR(INDEX(Cat_Productos!$B$2:$B$6,MATCH(G7,Cat_Productos!$A$2:$A$6,0)),"") -> 290 | M7: =IF(L7="","",H7*L7) -> 580 | N7: =IF(M7="","",J7-M7) -> 660 | O7: =IFERROR(N7/J7,0) -> 0.53225806 | Q7: ventas enero FINAL FINAL.xlsx | R7: enero | S7: 173
A8: 46023 | B8: 2026 | C8: 1 | D8: Enero | E8: CDMX | F8: Ana Torres | G8: Teclado Mecánico | H8: 2 | I8: 1450 | J8: 2900 | K8: =H8*I8 -> 2900 | L8: =IFERROR(INDEX(Cat_Productos!$B$2:$B$6,MATCH(G8,Cat_Productos!$A$2:$A$6,0)),"") -> 780 | M8: =IF(L8="","",H8*L8) -> 1560 | N8: =IF(M8="","",J8-M8) -> 1340 | O8: =IFERROR(N8/J8,0) -> 0.46206897 | Q8: ventas enero FINAL FINAL.xlsx | R8: enero | S8: 130
A9: 46023 | B9: 2026 | C9: 1 | D9: Enero | E9: Guadalajara | F9: Juan Pérez | G9: Teclado Mecánico | H9: 4 | I9: 1450 | J9: 5800 | K9: =H9*I9 -> 5800 | L9: =IFERROR(INDEX(Cat_Productos!$B$2:$B$6,MATCH(G9,Cat_Productos!$A$2:$A$6,0)),"") -> 780 | M9: =IF(L9="","",H9*L9) -> 3120 | N9: =IF(M9="","",J9-M9) -> 2680 | O9: =IFERROR(N9/J9,0) -> 0.46206897 | Q9: ventas enero FINAL FINAL.xlsx | R9: enero | S9: 16
A10: 46023 | B10: 2026 | C10: 1 | D10: Enero | E10: Monterrey | F10: Sofía Martínez | G10: Teclado Mecánico | H10: 6 | I10: 1450 | J10: 8700 | K10: =H10*I10 -> 8700 | L10: =IFERROR(INDEX(Cat_Productos!$B$2:$B$6,MATCH(G10,Cat_Productos!$A$2:$A$6,0)),"") -> 780 | M10: =IF(L10="","",H10*L10) -> 4680 | N10: =IF(M10="","",J10-M10) -> 4020 | O10: =IFERROR(N10/J10,0) -> 0.46206897 | Q10: ventas enero FINAL FINAL.xlsx | R10: enero | S10: 56
A11: 46023 | B11: 2026 | C11: 1 | D11: Enero | E11: Guadalajara | F11: Juan Pérez | G11: Teclado Mecánico | H11: 2 | I11: 1450 | J11: 2900 | K11: =H11*I11 -> 2900 | L11: =IFERROR(INDEX(Cat_Productos!$B$2:$B$6,MATCH(G11,Cat_Productos!$A$2:$A$6,0)),"") -> 780 | M11: =IF(L11="","",H11*L11) -> 1560 | N11: =IF(M11="","",J11-M11) -> 1340 | O11: =IFERROR(N11/J11,0) -> 0.46206897 | Q11: ventas enero FINAL FINAL.xlsx | R11: enero | S11: 6
A12: 46025 | B12: 2026 | C12: 1 | D12: Enero | E12: Monterrey | F12: Sofía Martínez | G12: Teclado Mecánico | H12: 6 | I12: 1450 | J12: 8700 | K12: =H12*I12 -> 8700 | L12: =IFERROR(INDEX(Cat_Productos!$B$2:$B$6,MATCH(G12,Cat_Productos!$A$2:$A$6,0)),"") -> 780 | M12: =IF(L12="","",H12*L12) -> 4680 | N12: =IF(M12="","",J12-M12) -> 4020 | O12: =IFERROR(N12/J12,0) -> 0.46206897 | Q12: ventas enero FINAL FINAL.xlsx | R12: enero | S12: 53
A13: 46025 | B13: 2026 | C13: 1 | D13: Enero | E13: Guadalajara | F13: Juan Pérez | G13: Mouse Inalámbrico | H13: 4 | I13: 620 | J13: 2480 | K13: =H13*I13 -> 2480 | L13: =IFERROR(INDEX(Cat_Productos!$B$2:$B$6,MATCH(G13,Cat_Productos!$A$2:$A$6,0)),"") -> 290 | M13: =IF(L13="","",H13*L13) -> 1160 | N13: =IF(M13="","",J13-M13) -> 1320 | O13: =IFERROR(N13/J13,0) -> 0.53225806 | Q13: ventas enero FINAL FINAL.xlsx | R13: enero | S13: 33
... A103: 46037 | B103: 2026 | C103: 1 | D103: Enero | E103: CDMX | F103: Ana Torres | G103: Teclado Mecánico | H103: 2 | I103: 1450 | J103: 2900 | K103: =H103*I103 -> 2900 | L103: =IFERROR(INDEX(Cat_Productos!$B$2:$B$6,MATCH(G103,Cat_Productos!$A$2:$A$6,0)),"") -> 780 | M103: =IF(L103="","",H103*L103) -> 1560 | N103: =IF(M103="","",J103-M103) -> 1340 | O103: =IFERROR(N103/J103,0) -> 0.46206897 | Q103: ventas enero FINAL FINAL.xlsx | R103: enero | S103: 133
A104: 46037 | B104: 2026 | C104: 1 | D104: Enero | E104: Guadalajara | F104: Juan Pérez | G104: Laptop Pro 14 | H104: 1 | I104: 23900 | J104: 28900 | K104: =H104*I104 -> 23900 | L104: =IFERROR(INDEX(Cat_Productos!$B$2:$B$6,MATCH(G104,Cat_Productos!$A$2:$A$6,0)),"") -> 19200 | M104: =IF(L104="","",H104*L104) -> 19200 | N104: =IF(M104="","",J104-M104) -> 9700 | O104: =IFERROR(N104/J104,0) -> 0.33564014 | Q104: ventas enero FINAL FINAL.xlsx | R104: enero | S104: 5 | T104: IMPORTE NO CUADRA
A105: 46037 | B105: 2026 | C105: 1 | D105: Enero | E105: CDMX | F105: Ana Torres | G105: Mouse Inalámbrico | H105: 2 | I105: 620 | J105: 1240 | K105: =H105*I105 -> 1240 | L105: =IFERROR(INDEX(Cat_Productos!$B$2:$B$6,MATCH(G105,Cat_Productos!$A$2:$A$6,0)),"") -> 290 | M105: =IF(L105="","",H105*L105) -> 580 | N105: =IF(M105="","",J105-M105) -> 660 | O105: =IFERROR(N105/J105,0) -> 0.53225806 | Q105: ventas enero FINAL FINAL.xlsx | R105: enero | S105: 143
A106: 46037 | B106: 2026 | C106: 1 | D106: Enero | E106: CDMX | F106: María López | G106: Mouse Inalámbrico | H106: 6 | I106: 620 | J106: 3720 | K106: =H106*I106 -> 3720 | L106: =IFERROR(INDEX(Cat_Productos!$B$2:$B$6,MATCH(G106,Cat_Productos!$A$2:$A$6,0)),"") -> 290 | M106: =IF(L106="","",H106*L106) -> 1740 | N106: =IF(M106="","",J106-M106) -> 1980 | O106: =IFERROR(N106/J106,0) -> 0.53225806 | Q106: ventas enero FINAL FINAL.xlsx | R106: enero | S106: 95
A107: 46037 | B107: 2026 | C107: 1 | D107: Enero | E107: CDMX | F107: Ana Torres | G107: Mouse Inalámbrico | H107: 2 | I107: 620 | J107: 1240 | K107: =H107*I107 -> 1240 | L107: =IFERROR(INDEX(Cat_Productos!$B$2:$B$6,MATCH(G107,Cat_Productos!$A$2:$A$6,0)),"") -> 290 | M107: =IF(L107="","",H107*L107) -> 580 | N107: =IF(M107="","",J107-M107) -> 660 | O107: =IFERROR(N107/J107,0) -> 0.53225806 | Q107: ventas enero FINAL FINAL.xlsx | R107: enero | S107: 159
A108: 46037 | B108: 2026 | C108: 1 | D108: Enero | E108: CDMX | F108: María López | G108: Mouse Inalámbrico | H108: 2 | I108: 620 | J108: 1240 | K108: =H108*I108 -> 1240 | L108: =IFERROR(INDEX(Cat_Productos!$B$2:$B$6,MATCH(G108,Cat_Productos!$A$2:$A$6,0)),"") -> 290 | M108: =IF(L108="","",H108*L108) -> 580 | N108: =IF(M108="","",J108-M108) -> 660 | O108: =IFERROR(N108/J108,0) -> 0.53225806 | Q108: ventas enero FINAL FINAL.xlsx | R108: enero | S108: 99
A109: 46037 | B109: 2026 | C109: 1 | D109: Enero | E109: Monterrey | F109: Carlos Ruiz | G109: Laptop Pro 14 | H109: 6 | I109: 23900 | J109: 143400 | K109: =H109*I109 -> 143400 | L109: =IFERROR(INDEX(Cat_Productos!$B$2:$B$6,MATCH(G109,Cat_Productos!$A$2:$A$6,0)),"") -> 19200 | M109: =IF(L109="","",H109*L109) -> 115200 | N109: =IF(M109="","",J109-M109) -> 28200 | O109: =IFERROR(N109/J109,0) -> 0.19665272 | Q109: ventas enero FINAL FINAL.xlsx | R109: enero | S109: 162
A110: 46037 | B110: 2026 | C110: 1 | D110: Enero | E110: CDMX | F110: María López | G110: Mouse Inalámbrico | H110: 4 | I110: 620 | J110: 2480 | K110: =H110*I110 -> 2480 | L110: =IFERROR(INDEX(Cat_Productos!$B$2:$B$6,MATCH(G110,Cat_Productos!$A$2:$A$6,0)),"") -> 290 | M110: =IF(L110="","",H110*L110) -> 1160 | N110: =IF(M110="","",J110-M110) -> 1320 | O110: =IFERROR(N110/J110,0) -> 0.53225806 | Q110: ventas enero FINAL FINAL.xlsx | R110: enero | S110: 105
A111: 46039 | B111: 2026 | C111: 1 | D111: Enero | E111: Monterrey | F111: Sofía Martínez | G111: Mouse Inalámbrico | H111: 6 | I111: 620 | J111: 3720 | K111: =H111*I111 -> 3720 | L111: =IFERROR(INDEX(Cat_Productos!$B$2:$B$6,MATCH(G111,Cat_Productos!$A$2:$A$6,0)),"") -> 290 | M111: =IF(L111="","",H111*L111) -> 1740 | N111: =IF(M111="","",J111-M111) -> 1980 | O111: =IFERROR(N111/J111,0) -> 0.53225806 | Q111: ventas enero FINAL FINAL.xlsx | R111: enero | S111: 66
A112: 46039 | B112: 2026 | C112: 1 | D112: Enero | E112: CDMX | F112: Ana Torres | G112: Mouse Inalámbrico | H112: 4 | I112: 620 | J112: 2480 | K112: =H112*I112 -> 2480 | L112: =IFERROR(INDEX(Cat_Productos!$B$2:$B$6,MATCH(G112,Cat_Productos!$A$2:$A$6,0)),"") -> 290 | M112: =IF(L112="","",H112*L112) -> 1160 | N112: =IF(M112="","",J112-M112) -> 1320 | O112: =IFERROR(N112/J112,0) -> 0.53225806 | Q112: ventas enero FINAL FINAL.xlsx | R112: enero | S112: 148
A113: 46039 | B113: 2026 | C113: 1 | D113: Enero | E113: CDMX | F113: María López | G113: Teclado Mecánico | H113: 2 | I113: 1450 | J113: 2900 | K113: =H113*I113 -> 2900 | L113: =IFERROR(INDEX(Cat_Productos!$B$2:$B$6,MATCH(G113,Cat_Productos!$A$2:$A$6,0)),"") -> 780 | M113: =IF(L113="","",H113*L113) -> 1560 | N113: =IF(M113="","",J113-M113) -> 1340 | O113: =IFERROR(N113/J113,0) -> 0.46206897 | Q113: ventas enero FINAL FINAL.xlsx | R113: enero | S113: 90
A114: 46039 | B114: 2026 | C114: 1 | D114: Enero | E114: Monterrey | F114: Sofía Martínez | G114: Mouse Inalámbrico | H114: 2 | I114: 620 | J114: 1240 | K114: =H114*I114 -> 1240 | L114: =IFERROR(INDEX(Cat_Productos!$B$2:$B$6,MATCH(G114,Cat_Productos!$A$2:$A$6,0)),"") -> 290 | M114: =IF(L114="","",H114*L114) -> 580 | N114: =IF(M114="","",J114-M114) -> 660 | O114: =IFERROR(N114/J114,0) -> 0.53225806 | Q114: ventas enero FINAL FINAL.xlsx | R114: enero | S114: 70
A115: 46039 | B115: 2026 | C115: 1 | D115: Enero | E115: Monterrey | F115: Sofía Martínez | G115: Mouse Inalámbrico | H115: 1 | I115: 620 | J115: 620 | K115: =H115*I115 -> 620 | L115: =IFERROR(INDEX(Cat_Productos!$B$2:$B$6,MATCH(G115,Cat_Productos!$A$2:$A$6,0)),"") -> 290 | M115: =IF(L115="","",H115*L115) -> 290 | N115: =IF(M115="","",J115-M115) -> 330 | O115: =IFERROR(N115/J115,0) -> 0.53225806 | Q115: ventas enero FINAL FINAL.xlsx | R115: enero | S115: 74
A116: 46039 | B116: 2026 | C116: 1 | D116: Enero | E116: CDMX | F116: María López | G116: Teclado Mecánico | H116: 6 | I116: 1450 | J116: 8700 | K116: =H116*I116 -> 8700 | L116: =IFERROR(INDEX(Cat_Productos!$B$2:$B$6,MATCH(G116,Cat_Productos!$A$2:$A$6,0)),"") -> 780 | M116: =IF(L116="","",H116*L116) -> 4680 | N116: =IF(M116="","",J116-M116) -> 4020 | O116: =IFERROR(N116/J116,0) -> 0.46206897 | Q116: ventas enero FINAL FINAL.xlsx | R116: enero | S116: 84
... A159: 46045 | B159: 2026 | C159: 1 | D159: Enero | E159: Guadalajara | F159: Juan Pérez | G159: Mouse Inalámbrico | H159: 2 | I159: 620 | J159: 1240 | K159: =H159*I159 -> 1240 | L159: =IFERROR(INDEX(Cat_Productos!$B$2:$B$6,MATCH(G159,Cat_Productos!$A$2:$A$6,0)),"") -> 290 | M159: =IF(L159="","",H159*L159) -> 580 | N159: =IF(M159="","",J159-M159) -> 660 | O159: =IFERROR(N159/J159,0) -> 0.53225806 | Q159: ventas enero FINAL FINAL.xlsx | R159: enero | S159: 41
A160: 46045 | B160: 2026 | C160: 1 | D160: Enero | E160: Guadalajara | F160: Juan Pérez | G160: Teclado Mecánico | H160: 4 | I160: 1450 | J160: 4620 | K160: =H160*I160 -> 5800 | L160: =IFERROR(INDEX(Cat_Productos!$B$2:$B$6,MATCH(G160,Cat_Productos!$A$2:$A$6,0)),"") -> 780 | M160: =IF(L160="","",H160*L160) -> 3120 | N160: =IF(M160="","",J160-M160) -> 1500 | O160: =IFERROR(N160/J160,0) -> 0.32467532 | Q160: ventas enero FINAL FINAL.xlsx | R160: enero | S160: 9 | T160: IMPORTE NO CUADRA
A161: 46047 | B161: 2026 | C161: 1 | D161: Enero | E161: CDMX | F161: Ana Torres | G161: Mouse Inalámbrico | H161: 6 | I161: 620 | J161: 3720 | K161: =H161*I161 -> 3720 | L161: =IFERROR(INDEX(Cat_Productos!$B$2:$B$6,MATCH(G161,Cat_Productos!$A$2:$A$6,0)),"") -> 290 | M161: =IF(L161="","",H161*L161) -> 1740 | N161: =IF(M161="","",J161-M161) -> 1980 | O161: =IFERROR(N161/J161,0) -> 0.53225806 | Q161: ventas enero FINAL FINAL.xlsx | R161: enero | S161: 160
A162: 46047 | B162: 2026 | C162: 1 | D162: Enero | E162: CDMX | F162: María López | G162: Mouse Inalámbrico | H162: 4 | I162: 620 | J162: 2480 | K162: =H162*I162 -> 2480 | L162: =IFERROR(INDEX(Cat_Productos!$B$2:$B$6,MATCH(G162,Cat_Productos!$A$2:$A$6,0)),"") -> 290 | M162: =IF(L162="","",H162*L162) -> 1160 | N162: =IF(M162="","",J162-M162) -> 1320 | O162: =IFERROR(N162/J162,0) -> 0.53225806 | Q162: ventas enero FINAL FINAL.xlsx | R162: enero | S162: 100
A163: 46047 | B163: 2026 | C163: 1 | D163: Enero | E163: Guadalajara | F163: Juan Pérez | G163: Mouse Inalámbrico | H163: 6 | I163: 620 | J163: 3720 | K163: =H163*I163 -> 3720 | L163: =IFERROR(INDEX(Cat_Productos!$B$2:$B$6,MATCH(G163,Cat_Productos!$A$2:$A$6,0)),"") -> 290 | M163: =IF(L163="","",H163*L163) -> 1740 | N163: =IF(M163="","",J163-M163) -> 1980 | O163: =IFERROR(N163/J163,0) -> 0.53225806 | Q163: ventas enero FINAL FINAL.xlsx | R163: enero | S163: 42
A164: 46047 | B164: 2026 | C164: 1 | D164: Enero | E164: CDMX | F164: María López | G164: Teclado Mecánico | H164: 2 | I164: 1450 | J164: 2900 | K164: =H164*I164 -> 2900 | L164: =IFERROR(INDEX(Cat_Productos!$B$2:$B$6,MATCH(G164,Cat_Productos!$A$2:$A$6,0)),"") -> 780 | M164: =IF(L164="","",H164*L164) -> 1560 | N164: =IF(M164="","",J164-M164) -> 1340 | O164: =IFERROR(N164/J164,0) -> 0.46206897 | Q164: ventas enero FINAL FINAL.xlsx | R164: enero | S164: 94
A165: 46047 | B165: 2026 | C165: 1 | D165: Enero | E165: CDMX | F165: María López | G165: Teclado Mecánico | H165: 6 | I165: 1450 | J165: 8700 | K165: =H165*I165 -> 8700 | L165: =IFERROR(INDEX(Cat_Productos!$B$2:$B$6,MATCH(G165,Cat_Productos!$A$2:$A$6,0)),"") -> 780 | M165: =IF(L165="","",H165*L165) -> 4680 | N165: =IF(M165="","",J165-M165) -> 4020 | O165: =IFERROR(N165/J165,0) -> 0.46206897 | Q165: ventas enero FINAL FINAL.xlsx | R165: enero | S165: 92
A166: 46047 | B166: 2026 | C166: 1 | D166: Enero | E166: CDMX | F166: María López | G166: Teclado Mecánico | H166: 6 | I166: 1450 | J166: 8700 | K166: =H166*I166 -> 8700 | L166: =IFERROR(INDEX(Cat_Productos!$B$2:$B$6,MATCH(G166,Cat_Productos!$A$2:$A$6,0)),"") -> 780 | M166: =IF(L166="","",H166*L166) -> 4680 | N166: =IF(M166="","",J166-M166) -> 4020 | O166: =IFERROR(N166/J166,0) -> 0.46206897 | Q166: ventas enero FINAL FINAL.xlsx | R166: enero | S166: 86
A167: 46047 | B167: 2026 | C167: 1 | D167: Enero | E167: Guadalajara | F167: Juan Pérez | G167: Teclado Mecánico | H167: 2 | I167: 1450 | J167: 2900 | K167: =H167*I167 -> 2900 | L167: =IFERROR(INDEX(Cat_Productos!$B$2:$B$6,MATCH(G167,Cat_Productos!$A$2:$A$6,0)),"") -> 780 | M167: =IF(L167="","",H167*L167) -> 1560 | N167: =IF(M167="","",J167-M167) -> 1340 | O167: =IFERROR(N167/J167,0) -> 0.46206897 | Q167: ventas enero FINAL FINAL.xlsx | R167: enero | S167: 10
A168: 46047 | B168: 2026 | C168: 1 | D168: Enero | E168: CDMX | F168: María López | G168: Teclado Mecánico | H168: 2 | I168: 1450 | J168: 2900 | K168: =H168*I168 -> 2900 | L168: =IFERROR(INDEX(Cat_Productos!$B$2:$B$6,MATCH(G168,Cat_Productos!$A$2:$A$6,0)),"") -> 780 | M168: =IF(L168="","",H168*L168) -> 1560 | N168: =IF(M168="","",J168-M168) -> 1340 | O168: =IFERROR(N168/J168,0) -> 0.46206897 | Q168: ventas enero FINAL FINAL.xlsx | R168: enero | S168: 82
A169: 46047 | B169: 2026 | C169: 1 | D169: Enero | E169: CDMX | F169: María López | G169: Laptop Pro 14 | H169: 6 | I169: 23900 | J169: 143400 | K169: =H169*I169 -> 143400 | L169: =IFERROR(INDEX(Cat_Productos!$B$2:$B$6,MATCH(G169,Cat_Productos!$A$2:$A$6,0)),"") -> 19200 | M169: =IF(L169="","",H169*L169) -> 115200 | N169: =IF(M169="","",J169-M169) -> 28200 | O169: =IFERROR(N169/J169,0) -> 0.19665272 | Q169: ventas enero FINAL FINAL.xlsx | R169: enero | S169: 76
A170: 46047 | B170: 2026 | C170: 1 | D170: Enero | E170: CDMX | F170: Ana Torres | G170: Teclado Mecánico | H170: 2 | I170: 1450 | J170: 2900 | K170: =H170*I170 -> 2900 | L170: =IFERROR(INDEX(Cat_Productos!$B$2:$B$6,MATCH(G170,Cat_Productos!$A$2:$A$6,0)),"") -> 780 | M170: =IF(L170="","",H170*L170) -> 1560 | N170: =IF(M170="","",J170-M170) -> 1340 | O170: =IFERROR(N170/J170,0) -> 0.46206897 | Q170: ventas enero FINAL FINAL.xlsx | R170: enero | S170: 124
A171: 46047 | B171: 2026 | C171: 1 | D171: Enero | E171: CDMX | F171: Ana Torres | G171: Mouse Inalámbrico | H171: 4 | I171: 620 | J171: 2480 | K171: =H171*I171 -> 2480 | L171: =IFERROR(INDEX(Cat_Productos!$B$2:$B$6,MATCH(G171,Cat_Productos!$A$2:$A$6,0)),"") -> 290 | M171: =IF(L171="","",H171*L171) -> 1160 | N171: =IF(M171="","",J171-M171) -> 1320 | O171: =IFERROR(N171/J171,0) -> 0.53225806 | Q171: ventas enero FINAL FINAL.xlsx | R171: enero | S171: 144
A172: 46047 | B172: 2026 | C172: 1 | D172: Enero | E172: CDMX | F172: Ana Torres | G172: Laptop Pro 14 | H172: 2 | I172: 23900 | J172: 47800 | K172: =H172*I172 -> 47800 | L172: =IFERROR(INDEX(Cat_Productos!$B$2:$B$6,MATCH(G172,Cat_Productos!$A$2:$A$6,0)),"") -> 19200 | M172: =IF(L172="","",H172*L172) -> 38400 | N172: =IF(M172="","",J172-M172) -> 9400 | O172: =IFERROR(N172/J172,0) -> 0.19665272 | Q172: ventas enero FINAL FINAL.xlsx | R172: enero | S172: 112
... A489: 46098 | B489: 2026 | C489: 3 | D489: Marzo | E489: CDMX | F489: Ana Torres | G489: Teclado Mecánico | H489: 4 | I489: 1450 | J489: 5800 | K489: =H489*I489 -> 5800 | L489: =IFERROR(INDEX(Cat_Productos!$B$2:$B$6,MATCH(G489,Cat_Productos!$A$2:$A$6,0)),"") -> 780 | M489: =IF(L489="","",H489*L489) -> 3120 | N489: =IF(M489="","",J489-M489) -> 2680 | O489: =IFERROR(N489/J489,0) -> 0.46206897 | Q489: marzo_ventas.csv | R489: - | S489: 157
A490: 46098 | B490: 2026 | C490: 3 | D490: Marzo | E490: CDMX | F490: Ana Torres | G490: Laptop Pro 14 | H490: -1 | I490: 24500 | J490: -24500 | K490: =H490*I490 -> -24500 | L490: =IFERROR(INDEX(Cat_Productos!$B$2:$B$6,MATCH(G490,Cat_Productos!$A$2:$A$6,0)),"") -> 19200 | M490: =IF(L490="","",H490*L490) -> -19200 | N490: =IF(M490="","",J490-M490) -> -5300 | O490: =IFERROR(N490/J490,0) -> 0.21632653 | P490: DEVOLUCION | Q490: marzo_ventas.csv | R490: - | S490: 225 | T490: DEVOLUCION
A491: 46098 | B491: 2026 | C491: 3 | D491: Marzo | E491: Guadalajara | F491: Juan Pérez | G491: Laptop Pro 14 | H491: 4 | I491: 24500 | J491: 98000 | K491: =H491*I491 -> 98000 | L491: =IFERROR(INDEX(Cat_Productos!$B$2:$B$6,MATCH(G491,Cat_Productos!$A$2:$A$6,0)),"") -> 19200 | M491: =IF(L491="","",H491*L491) -> 76800 | N491: =IF(M491="","",J491-M491) -> 21200 | O491: =IFERROR(N491/J491,0) -> 0.21632653 | Q491: marzo_ventas.csv | R491: - | S491: 3
A492: 46098 | B492: 2026 | C492: 3 | D492: Marzo | E492: CDMX | F492: Ana Torres | G492: Mouse Inalámbrico | H492: 4 | I492: 620 | J492: 2480 | K492: =H492*I492 -> 2480 | L492: =IFERROR(INDEX(Cat_Productos!$B$2:$B$6,MATCH(G492,Cat_Productos!$A$2:$A$6,0)),"") -> 290 | M492: =IF(L492="","",H492*L492) -> 1160 | N492: =IF(M492="","",J492-M492) -> 1320 | O492: =IFERROR(N492/J492,0) -> 0.53225806 | Q492: marzo_ventas.csv | R492: - | S492: 163
A493: 46098 | B493: 2026 | C493: 3 | D493: Marzo | E493: CDMX | F493: María López | G493: Mouse Inalámbrico | H493: 4 | I493: 620 | J493: 2480 | K493: =H493*I493 -> 2480 | L493: =IFERROR(INDEX(Cat_Productos!$B$2:$B$6,MATCH(G493,Cat_Productos!$A$2:$A$6,0)),"") -> 290 | M493: =IF(L493="","",H493*L493) -> 1160 | N493: =IF(M493="","",J493-M493) -> 1320 | O493: =IFERROR(N493/J493,0) -> 0.53225806 | Q493: marzo_ventas.csv | R493: - | S493: 125
A494: 46098 | B494: 2026 | C494: 3 | D494: Marzo | E494: Monterrey | F494: Sofía Martínez | G494: Mouse Inalámbrico | H494: 4 | I494: 620 | J494: 2480 | K494: =H494*I494 -> 2480 | L494: =IFERROR(INDEX(Cat_Productos!$B$2:$B$6,MATCH(G494,Cat_Productos!$A$2:$A$6,0)),"") -> 290 | M494: =IF(L494="","",H494*L494) -> 1160 | N494: =IF(M494="","",J494-M494) -> 1320 | O494: =IFERROR(N494/J494,0) -> 0.53225806 | Q494: marzo_ventas.csv | R494: - | S494: 84
A495: 46098 | B495: 2026 | C495: 3 | D495: Marzo | E495: Guadalajara | F495: Juan Pérez | G495: Mouse Inalámbrico | H495: 2 | I495: 620 | J495: 1240 | K495: =H495*I495 -> 1240 | L495: =IFERROR(INDEX(Cat_Productos!$B$2:$B$6,MATCH(G495,Cat_Productos!$A$2:$A$6,0)),"") -> 290 | M495: =IF(L495="","",H495*L495) -> 580 | N495: =IF(M495="","",J495-M495) -> 660 | O495: =IFERROR(N495/J495,0) -> 0.53225806 | Q495: marzo_ventas.csv | R495: - | S495: 55
A496: 46098 | B496: 2026 | C496: 3 | D496: Marzo | E496: CDMX | F496: María López | G496: Mouse Inalámbrico | H496: 4 | I496: 620 | J496: 2480 | K496: =H496*I496 -> 2480 | L496: =IFERROR(INDEX(Cat_Productos!$B$2:$B$6,MATCH(G496,Cat_Productos!$A$2:$A$6,0)),"") -> 290 | M496: =IF(L496="","",H496*L496) -> 1160 | N496: =IF(M496="","",J496-M496) -> 1320 | O496: =IFERROR(N496/J496,0) -> 0.53225806 | Q496: marzo_ventas.csv | R496: - | S496: 121
A497: 46098 | B497: 2026 | C497: 3 | D497: Marzo | E497: CDMX | F497: María López | G497: Teclado Mecánico | H497: 6 | I497: 1450 | J497: 8700 | K497: =H497*I497 -> 8700 | L497: =IFERROR(INDEX(Cat_Productos!$B$2:$B$6,MATCH(G497,Cat_Productos!$A$2:$A$6,0)),"") -> 780 | M497: =IF(L497="","",H497*L497) -> 4680 | N497: =IF(M497="","",J497-M497) -> 4020 | O497: =IFERROR(N497/J497,0) -> 0.46206897 | Q497: marzo_ventas.csv | R497: - | S497: 115
A498: 46098 | B498: 2026 | C498: 3 | D498: Marzo | E498: Guadalajara | F498: Juan Pérez | G498: Laptop Pro 14 | H498: 1 | I498: 24500 | J498: 24500 | K498: =H498*I498 -> 24500 | L498: =IFERROR(INDEX(Cat_Productos!$B$2:$B$6,MATCH(G498,Cat_Productos!$A$2:$A$6,0)),"") -> 19200 | M498: =IF(L498="","",H498*L498) -> 19200 | N498: =IF(M498="","",J498-M498) -> 5300 | O498: =IFERROR(N498/J498,0) -> 0.21632653 | Q498: marzo_ventas.csv | R498: - | S498: 7
A499: 46098 | B499: 2026 | C499: 3 | D499: Marzo | E499: Monterrey | F499: Sofía Martínez | G499: Teclado Mecánico | H499: 4 | I499: 1450 | J499: 5800 | K499: =H499*I499 -> 5800 | L499: =IFERROR(INDEX(Cat_Productos!$B$2:$B$6,MATCH(G499,Cat_Productos!$A$2:$A$6,0)),"") -> 780 | M499: =IF(L499="","",H499*L499) -> 3120 | N499: =IF(M499="","",J499-M499) -> 2680 | O499: =IFERROR(N499/J499,0) -> 0.46206897 | Q499: marzo_ventas.csv | R499: - | S499: 66
A500: 46098 | B500: 2026 | C500: 3 | D500: Marzo | E500: Monterrey | F500: Sofía Martínez | G500: Teclado Mecánico | H500: 6 | I500: 1450 | J500: 8700 | K500: =H500*I500 -> 8700 | L500: =IFERROR(INDEX(Cat_Productos!$B$2:$B$6,MATCH(G500,Cat_Productos!$A$2:$A$6,0)),"") -> 780 | M500: =IF(L500="","",H500*L500) -> 4680 | N500: =IF(M500="","",J500-M500) -> 4020 | O500: =IFERROR(N500/J500,0) -> 0.46206897 | Q500: marzo_ventas.csv | R500: - | S500: 74
A501: 46098 | B501: 2026 | C501: 3 | D501: Marzo | E501: Monterrey | F501: Sofía Martínez | G501: Teclado Mecánico | H501: 6 | I501: 1450 | J501: 8700 | K501: =H501*I501 -> 8700 | L501: =IFERROR(INDEX(Cat_Productos!$B$2:$B$6,MATCH(G501,Cat_Productos!$A$2:$A$6,0)),"") -> 780 | M501: =IF(L501="","",H501*L501) -> 4680 | N501: =IF(M501="","",J501-M501) -> 4020 | O501: =IFERROR(N501/J501,0) -> 0.46206897 | Q501: marzo_ventas.csv | R501: - | S501: 78
A502: 46098 | B502: 2026 | C502: 3 | D502: Marzo | E502: Guadalajara | F502: Luis Gómez | G502: Teclado Mecánico | H502: 2 | I502: 1450 | J502: 2900 | K502: =H502*I502 -> 2900 | L502: =IFERROR(INDEX(Cat_Productos!$B$2:$B$6,MATCH(G502,Cat_Productos!$A$2:$A$6,0)),"") -> 780 | M502: =IF(L502="","",H502*L502) -> 1560 | N502: =IF(M502="","",J502-M502) -> 1340 | O502: =IFERROR(N502/J502,0) -> 0.46206897 | Q502: marzo_ventas.csv | R502: - | S502: 192
... A767: 46140 | B767: 2026 | C767: 4 | D767: Abril | E767: Monterrey | F767: Sofía Martínez | G767: Webcam HD | H767: 1 | I767: 1180 | J767: 1180 | K767: =H767*I767 -> 1180 | L767: =IFERROR(INDEX(Cat_Productos!$B$2:$B$6,MATCH(G767,Cat_Productos!$A$2:$A$6,0)),"") -> 590 | M767: =IF(L767="","",H767*L767) -> 590 | N767: =IF(M767="","",J767-M767) -> 590 | O767: =IFERROR(N767/J767,0) -> 0.5 | Q767: Ventas_Abril_FINAL_v2.xlsx | R767: MTY | S767: 17
A768: 46143 | B768: 2026 | C768: 5 | D768: Mayo | E768: Guadalajara | F768: Carlos Ruiz | G768: Webcam HD | H768: 5 | I768: 1180 | J768: 5900 | K768: =H768*I768 -> 5900 | L768: =IFERROR(INDEX(Cat_Productos!$B$2:$B$6,MATCH(G768,Cat_Productos!$A$2:$A$6,0)),"") -> 590 | M768: =IF(L768="","",H768*L768) -> 2950 | N768: =IF(M768="","",J768-M768) -> 2950 | O768: =IFERROR(N768/J768,0) -> 0.5 | Q768: Ventas_Mayo_2026 - Ventas Mayo.csv | R768: - | S768: 94 | T768: IMPORTE CALCULADO
A769: 46143 | B769: 2026 | C769: 5 | D769: Mayo | E769: CDMX | F769: Juan Pérez | G769: Monitor 27" | H769: 4 | I769: 6200 | J769: 24800 | K769: =H769*I769 -> 24800 | L769: =IFERROR(INDEX(Cat_Productos!$B$2:$B$6,MATCH(G769,Cat_Productos!$A$2:$A$6,0)),"") -> 4100 | M769: =IF(L769="","",H769*L769) -> 16400 | N769: =IF(M769="","",J769-M769) -> 8400 | O769: =IFERROR(N769/J769,0) -> 0.33870968 | Q769: Ventas_Mayo_2026 - Ventas Mayo.csv | R769: - | S769: 108 | T769: IMPORTE CALCULADO
A770: 46144 | B770: 2026 | C770: 5 | D770: Mayo | E770: Monterrey | F770: María López | G770: Teclado Mecánico | H770: 1 | I770: 1450 | J770: 1450 | K770: =H770*I770 -> 1450 | L770: =IFERROR(INDEX(Cat_Productos!$B$2:$B$6,MATCH(G770,Cat_Productos!$A$2:$A$6,0)),"") -> 780 | M770: =IF(L770="","",H770*L770) -> 780 | N770: =IF(M770="","",J770-M770) -> 670 | O770: =IFERROR(N770/J770,0) -> 0.46206897 | Q770: Ventas_Mayo_2026 - Ventas Mayo.csv | R770: - | S770: 57
A771: 46144 | B771: 2026 | C771: 5 | D771: Mayo | E771: Guadalajara | F771: Ana Torres | G771: Teclado Mecánico | H771: 2 | I771: 1450 | J771: 2900 | K771: =H771*I771 -> 2900 | L771: =IFERROR(INDEX(Cat_Productos!$B$2:$B$6,MATCH(G771,Cat_Productos!$A$2:$A$6,0)),"") -> 780 | M771: =IF(L771="","",H771*L771) -> 1560 | N771: =IF(M771="","",J771-M771) -> 1340 | O771: =IFERROR(N771/J771,0) -> 0.46206897 | Q771: Ventas_Mayo_2026 - Ventas Mayo.csv | R771: - | S771: 75
A772: 46144 | B772: 2026 | C772: 5 | D772: Mayo | E772: Monterrey | F772: Sofía Martínez | G772: Webcam HD | H772: 1 | I772: 1180 | J772: 1180 | K772: =H772*I772 -> 1180 | L772: =IFERROR(INDEX(Cat_Productos!$B$2:$B$6,MATCH(G772,Cat_Productos!$A$2:$A$6,0)),"") -> 590 | M772: =IF(L772="","",H772*L772) -> 590 | N772: =IF(M772="","",J772-M772) -> 590 | O772: =IFERROR(N772/J772,0) -> 0.5 | Q772: Ventas_Mayo_2026 - Ventas Mayo.csv | R772: - | S772: 3
A773: 46145 | B773: 2026 | C773: 5 | D773: Mayo | E773: Monterrey | F773: Sofía Martínez | G773: Teclado Mecánico | H773: 2 | I773: 1450 | J773: 2900 | K773: =H773*I773 -> 2900 | L773: =IFERROR(INDEX(Cat_Productos!$B$2:$B$6,MATCH(G773,Cat_Productos!$A$2:$A$6,0)),"") -> 780 | M773: =IF(L773="","",H773*L773) -> 1560 | N773: =IF(M773="","",J773-M773) -> 1340 | O773: =IFERROR(N773/J773,0) -> 0.46206897 | Q773: Ventas_Mayo_2026 - Ventas Mayo.csv | R773: - | S773: 66
A774: 46145 | B774: 2026 | C774: 5 | D774: Mayo | E774: CDMX | F774: Luis Gómez | G774: Monitor 27" | H774: 6 | I774: 6200 | J774: 37200 | K774: =H774*I774 -> 37200 | L774: =IFERROR(INDEX(Cat_Productos!$B$2:$B$6,MATCH(G774,Cat_Productos!$A$2:$A$6,0)),"") -> 4100 | M774: =IF(L774="","",H774*L774) -> 24600 | N774: =IF(M774="","",J774-M774) -> 12600 | O774: =IFERROR(N774/J774,0) -> 0.33870968 | Q774: Ventas_Mayo_2026 - Ventas Mayo.csv | R774: - | S774: 27
A775: 46145 | B775: 2026 | C775: 5 | D775: Mayo | E775: CDMX | F775: Ana Torres | G775: Mouse Inalámbrico | H775: 3 | I775: 620 | J775: 1860 | K775: =H775*I775 -> 1860 | L775: =IFERROR(INDEX(Cat_Productos!$B$2:$B$6,MATCH(G775,Cat_Productos!$A$2:$A$6,0)),"") -> 290 | M775: =IF(L775="","",H775*L775) -> 870 | N775: =IF(M775="","",J775-M775) -> 990 | O775: =IFERROR(N775/J775,0) -> 0.53225806 | Q775: Ventas_Mayo_2026 - Ventas Mayo.csv | R775: - | S775: 26
A776: 46145 | B776: 2026 | C776: 5 | D776: Mayo | E776: CDMX | F776: Carlos Ruiz | G776: Mouse Inalámbrico | H776: 3 | I776: 620 | J776: 1860 | K776: =H776*I776 -> 1860 | L776: =IFERROR(INDEX(Cat_Productos!$B$2:$B$6,MATCH(G776,Cat_Productos!$A$2:$A$6,0)),"") -> 290 | M776: =IF(L776="","",H776*L776) -> 870 | N776: =IF(M776="","",J776-M776) -> 990 | O776: =IFERROR(N776/J776,0) -> 0.53225806 | Q776: Ventas_Mayo_2026 - Ventas Mayo.csv | R776: - | S776: 118
A777: 46145 | B777: 2026 | C777: 5 | D777: Mayo | E777: Monterrey | F777: Luis Gómez | G777: Mouse Inalámbrico | H777: 5 | I777: 620 | J777: 3100 | K777: =H777*I777 -> 3100 | L777: =IFERROR(INDEX(Cat_Productos!$B$2:$B$6,MATCH(G777,Cat_Productos!$A$2:$A$6,0)),"") -> 290 | M777: =IF(L777="","",H777*L777) -> 1450 | N777: =IF(M777="","",J777-M777) -> 1650 | O777: =IFERROR(N777/J777,0) -> 0.53225806 | Q777: Ventas_Mayo_2026 - Ventas Mayo.csv | R777: - | S777: 86
A778: 46145 | B778: 2026 | C778: 5 | D778: Mayo | E778: Guadalajara | F778: Juan Pérez | G778: Monitor 27" | H778: 4 | I778: 6200 | J778: 24800 | K778: =H778*I778 -> 24800 | L778: =IFERROR(INDEX(Cat_Productos!$B$2:$B$6,MATCH(G778,Cat_Productos!$A$2:$A$6,0)),"") -> 4100 | M778: =IF(L778="","",H778*L778) -> 16400 | N778: =IF(M778="","",J778-M778) -> 8400 | O778: =IFERROR(N778/J778,0) -> 0.33870968 | Q778: Ventas_Mayo_2026 - Ventas Mayo.csv | R778: - | S778: 17
A779: 46145 | B779: 2026 | C779: 5 | D779: Mayo | E779: Guadalajara | F779: Ana Torres | G779: Teclado Mecánico | H779: 2 | I779: 1450 | J779: 2900 | K779: =H779*I779 -> 2900 | L779: =IFERROR(INDEX(Cat_Productos!$B$2:$B$6,MATCH(G779,Cat_Productos!$A$2:$A$6,0)),"") -> 780 | M779: =IF(L779="","",H779*L779) -> 1560 | N779: =IF(M779="","",J779-M779) -> 1340 | O779: =IFERROR(N779/J779,0) -> 0.46206897 | Q779: Ventas_Mayo_2026 - Ventas Mayo.csv | R779: - | S779: 114
A780: 46145 | B780: 2026 | C780: 5 | D780: Mayo | E780: Monterrey | F780: Carlos Ruiz | G780: Webcam HD | H780: 4 | I780: 1180 | J780: 4720 | K780: =H780*I780 -> 4720 | L780: =IFERROR(INDEX(Cat_Productos!$B$2:$B$6,MATCH(G780,Cat_Productos!$A$2:$A$6,0)),"") -> 590 | M780: =IF(L780="","",H780*L780) -> 2360 | N780: =IF(M780="","",J780-M780) -> 2360 | O780: =IFERROR(N780/J780,0) -> 0.5 | Q780: Ventas_Mayo_2026 - Ventas Mayo.csv | R780: - | S780: 116
A781: 46146 | B781: 2026 | C781: 5 | D781: Mayo | E781: Monterrey | F781: Carlos Ruiz | G781: Webcam HD | H781: 2 | I781: 1180 | J781: 2360 | K781: =H781*I781 -> 2360 | L781: =IFERROR(INDEX(Cat_Productos!$B$2:$B$6,MATCH(G781,Cat_Productos!$A$2:$A$6,0)),"") -> 590 | M781: =IF(L781="","",H781*L781) -> 1180 | N781: =IF(M781="","",J781-M781) -> 1180 | O781: =IFERROR(N781/J781,0) -> 0.5 | Q781: Ventas_Mayo_2026 - Ventas Mayo.csv | R781: - | S781: 100
... A814: 46154 | B814: 2026 | C814: 5 | D814: Mayo | E814: Monterrey | F814: Carlos Ruiz | G814: Mouse Inalámbrico | H814: 4 | I814: 620 | J814: 2480 | K814: =H814*I814 -> 2480 | L814: =IFERROR(INDEX(Cat_Productos!$B$2:$B$6,MATCH(G814,Cat_Productos!$A$2:$A$6,0)),"") -> 290 | M814: =IF(L814="","",H814*L814) -> 1160 | N814: =IF(M814="","",J814-M814) -> 1320 | O814: =IFERROR(N814/J814,0) -> 0.53225806 | Q814: Ventas_Mayo_2026 - Ventas Mayo.csv | R814: - | S814: 59
A815: 46155 | B815: 2026 | C815: 5 | D815: Mayo | E815: CDMX | F815: Sofía Martínez | G815: Teclado Mecánico | H815: 3 | I815: 1450 | J815: 4350 | K815: =H815*I815 -> 4350 | L815: =IFERROR(INDEX(Cat_Productos!$B$2:$B$6,MATCH(G815,Cat_Productos!$A$2:$A$6,0)),"") -> 780 | M815: =IF(L815="","",H815*L815) -> 2340 | N815: =IF(M815="","",J815-M815) -> 2010 | O815: =IFERROR(N815/J815,0) -> 0.46206897 | Q815: Ventas_Mayo_2026 - Ventas Mayo.csv | R815: - | S815: 9 | T815: IMPORTE CALCULADO
A816: 46155 | B816: 2026 | C816: 5 | D816: Mayo | E816: CDMX | F816: Carlos Ruiz | G816: Monitor 27" | H816: 1 | I816: 6200 | J816: 6200 | K816: =H816*I816 -> 6200 | L816: =IFERROR(INDEX(Cat_Productos!$B$2:$B$6,MATCH(G816,Cat_Productos!$A$2:$A$6,0)),"") -> 4100 | M816: =IF(L816="","",H816*L816) -> 4100 | N816: =IF(M816="","",J816-M816) -> 2100 | O816: =IFERROR(N816/J816,0) -> 0.33870968 | Q816: Ventas_Mayo_2026 - Ventas Mayo.csv | R816: - | S816: 6
A817: 46155 | B817: 2026 | C817: 5 | D817: Mayo | E817: Monterrey | F817: Carlos Ruiz | G817: Teclado Mecánico | H817: 5 | I817: 1450 | J817: 7250 | K817: =H817*I817 -> 7250 | L817: =IFERROR(INDEX(Cat_Productos!$B$2:$B$6,MATCH(G817,Cat_Productos!$A$2:$A$6,0)),"") -> 780 | M817: =IF(L817="","",H817*L817) -> 3900 | N817: =IF(M817="","",J817-M817) -> 3350 | O817: =IFERROR(N817/J817,0) -> 0.46206897 | Q817: Ventas_Mayo_2026 - Ventas Mayo.csv | R817: - | S817: 58
A818: 46155 | B818: 2026 | C818: 5 | D818: Mayo | E818: CDMX | F818: Carlos Ruiz | G818: Monitor 27" | H818: 3 | I818: 6200 | J818: 18600 | K818: =H818*I818 -> 18600 | L818: =IFERROR(INDEX(Cat_Productos!$B$2:$B$6,MATCH(G818,Cat_Productos!$A$2:$A$6,0)),"") -> 4100 | M818: =IF(L818="","",H818*L818) -> 12300 | N818: =IF(M818="","",J818-M818) -> 6300 | O818: =IFERROR(N818/J818,0) -> 0.33870968 | Q818: Ventas_Mayo_2026 - Ventas Mayo.csv | R818: - | S818: 55
A819: 46155 | B819: 2026 | C819: 5 | D819: Mayo | E819: Monterrey | F819: Juan Pérez | G819: Webcam HD | H819: 1 | I819: 1180 | J819: 1180 | K819: =H819*I819 -> 1180 | L819: =IFERROR(INDEX(Cat_Productos!$B$2:$B$6,MATCH(G819,Cat_Productos!$A$2:$A$6,0)),"") -> 590 | M819: =IF(L819="","",H819*L819) -> 590 | N819: =IF(M819="","",J819-M819) -> 590 | O819: =IFERROR(N819/J819,0) -> 0.5 | Q819: Ventas_Mayo_2026 - Ventas Mayo.csv | R819: - | S819: 39
A820: 46156 | B820: 2026 | C820: 5 | D820: Mayo | E820: Monterrey | F820: Sofía Martínez | G820: Teclado Mecánico | H820: 6 | I820: 1450 | J820: 8700 | K820: =H820*I820 -> 8700 | L820: =IFERROR(INDEX(Cat_Productos!$B$2:$B$6,MATCH(G820,Cat_Productos!$A$2:$A$6,0)),"") -> 780 | M820: =IF(L820="","",H820*L820) -> 4680 | N820: =IF(M820="","",J820-M820) -> 4020 | O820: =IFERROR(N820/J820,0) -> 0.46206897 | Q820: Ventas_Mayo_2026 - Ventas Mayo.csv | R820: - | S820: 97
A821: 46156 | B821: 2026 | C821: 5 | D821: Mayo | E821: Guadalajara | F821: Juan Pérez | G821: Laptop Pro 14 | H821: 4 | I821: 24500 | J821: 98000 | K821: =H821*I821 -> 98000 | L821: =IFERROR(INDEX(Cat_Productos!$B$2:$B$6,MATCH(G821,Cat_Productos!$A$2:$A$6,0)),"") -> 19200 | M821: =IF(L821="","",H821*L821) -> 76800 | N821: =IF(M821="","",J821-M821) -> 21200 | O821: =IFERROR(N821/J821,0) -> 0.21632653 | Q821: Ventas_Mayo_2026 - Ventas Mayo.csv | R821: - | S821: 30
A822: 46156 | B822: 2026 | C822: 5 | D822: Mayo | E822: Guadalajara | F822: Ana Torres | G822: Laptop Pro 14 | H822: 5 | I822: 24500 | J822: 122500 | K822: =H822*I822 -> 122500 | L822: =IFERROR(INDEX(Cat_Productos!$B$2:$B$6,MATCH(G822,Cat_Productos!$A$2:$A$6,0)),"") -> 19200 | M822: =IF(L822="","",H822*L822) -> 96000 | N822: =IF(M822="","",J822-M822) -> 26500 | O822: =IFERROR(N822/J822,0) -> 0.21632653 | Q822: Ventas_Mayo_2026 - Ventas Mayo.csv | R822: - | S822: 63
A823: 46156 | B823: 2026 | C823: 5 | D823: Mayo | E823: CDMX | F823: Carlos Ruiz | G823: Mouse Inalámbrico | H823: 1 | I823: 620 | J823: 620 | K823: =H823*I823 -> 620 | L823: =IFERROR(INDEX(Cat_Productos!$B$2:$B$6,MATCH(G823,Cat_Productos!$A$2:$A$6,0)),"") -> 290 | M823: =IF(L823="","",H823*L823) -> 290 | N823: =IF(M823="","",J823-M823) -> 330 | O823: =IFERROR(N823/J823,0) -> 0.53225806 | Q823: Ventas_Mayo_2026 - Ventas Mayo.csv | R823: - | S823: 119
A824: 46157 | B824: 2026 | C824: 5 | D824: Mayo | E824: Monterrey | F824: Sofía Martínez | G824: Mouse Inalámbrico | H824: 1 | I824: 620 | J824: 620 | K824: =H824*I824 -> 620 | L824: =IFERROR(INDEX(Cat_Productos!$B$2:$B$6,MATCH(G824,Cat_Productos!$A$2:$A$6,0)),"") -> 290 | M824: =IF(L824="","",H824*L824) -> 290 | N824: =IF(M824="","",J824-M824) -> 330 | O824: =IFERROR(N824/J824,0) -> 0.53225806 | Q824: Ventas_Mayo_2026 - Ventas Mayo.csv | R824: - | S824: 113
A825: 46157 | B825: 2026 | C825: 5 | D825: Mayo | E825: Monterrey | F825: María López | G825: Monitor 27" | H825: 1 | I825: 6200 | J825: 6200 | K825: =H825*I825 -> 6200 | L825: =IFERROR(INDEX(Cat_Productos!$B$2:$B$6,MATCH(G825,Cat_Productos!$A$2:$A$6,0)),"") -> 4100 | M825: =IF(L825="","",H825*L825) -> 4100 | N825: =IF(M825="","",J825-M825) -> 2100 | O825: =IFERROR(N825/J825,0) -> 0.33870968 | Q825: Ventas_Mayo_2026 - Ventas Mayo.csv | R825: - | S825: 112
A826: 46158 | B826: 2026 | C826: 5 | D826: Mayo | E826: Monterrey | F826: Ana Torres | G826: Webcam HD | H826: 2 | I826: 1180 | J826: 2360 | K826: =H826*I826 -> 2360 | L826: =IFERROR(INDEX(Cat_Productos!$B$2:$B$6,MATCH(G826,Cat_Productos!$A$2:$A$6,0)),"") -> 590 | M826: =IF(L826="","",H826*L826) -> 1180 | N826: =IF(M826="","",J826-M826) -> 1180 | O826: =IFERROR(N826/J826,0) -> 0.5 | Q826: Ventas_Mayo_2026 - Ventas Mayo.csv | R826: - | S826: 77
A827: 46158 | B827: 2026 | C827: 5 | D827: Mayo | E827: Guadalajara | F827: Carlos Ruiz | G827: Monitor 27" | H827: 1 | I827: 6200 | J827: 6200 | K827: =H827*I827 -> 6200 | L827: =IFERROR(INDEX(Cat_Productos!$B$2:$B$6,MATCH(G827,Cat_Productos!$A$2:$A$6,0)),"") -> 4100 | M827: =IF(L827="","",H827*L827) -> 4100 | N827: =IF(M827="","",J827-M827) -> 2100 | O827: =IFERROR(N827/J827,0) -> 0.33870968 | Q827: Ventas_Mayo_2026 - Ventas Mayo.csv | R827: - | S827: 121
... A848: 46162 | B848: 2026 | C848: 5 | D848: Mayo | E848: Monterrey | F848: Ana Torres | G848: Mouse Inalámbrico | H848: 5 | I848: 620 | J848: 3100 | K848: =H848*I848 -> 3100 | L848: =IFERROR(INDEX(Cat_Productos!$B$2:$B$6,MATCH(G848,Cat_Productos!$A$2:$A$6,0)),"") -> 290 | M848: =IF(L848="","",H848*L848) -> 1450 | N848: =IF(M848="","",J848-M848) -> 1650 | O848: =IFERROR(N848/J848,0) -> 0.53225806 | Q848: Ventas_Mayo_2026 - Ventas Mayo.csv | R848: - | S848: 62
A849: 46162 | B849: 2026 | C849: 5 | D849: Mayo | E849: Monterrey | F849: Carlos Ruiz | G849: Monitor 27" | H849: 6 | I849: 6200 | J849: 37200 | K849: =H849*I849 -> 37200 | L849: =IFERROR(INDEX(Cat_Productos!$B$2:$B$6,MATCH(G849,Cat_Productos!$A$2:$A$6,0)),"") -> 4100 | M849: =IF(L849="","",H849*L849) -> 24600 | N849: =IF(M849="","",J849-M849) -> 12600 | O849: =IFERROR(N849/J849,0) -> 0.33870968 | Q849: Ventas_Mayo_2026 - Ventas Mayo.csv | R849: - | S849: 44 | T849: IMPORTE CALCULADO
A850: 46163 | B850: 2026 | C850: 5 | D850: Mayo | E850: CDMX | F850: Juan Pérez | G850: Mouse Inalámbrico | H850: 5 | I850: 620 | J850: 3100 | K850: =H850*I850 -> 3100 | L850: =IFERROR(INDEX(Cat_Productos!$B$2:$B$6,MATCH(G850,Cat_Productos!$A$2:$A$6,0)),"") -> 290 | M850: =IF(L850="","",H850*L850) -> 1450 | N850: =IF(M850="","",J850-M850) -> 1650 | O850: =IFERROR(N850/J850,0) -> 0.53225806 | Q850: Ventas_Mayo_2026 - Ventas Mayo.csv | R850: - | S850: 33
A851: 46163 | B851: 2026 | C851: 5 | D851: Mayo | E851: Guadalajara | F851: María López | G851: Laptop Pro 14 | H851: 1 | I851: 24500 | J851: 24500 | K851: =H851*I851 -> 24500 | L851: =IFERROR(INDEX(Cat_Productos!$B$2:$B$6,MATCH(G851,Cat_Productos!$A$2:$A$6,0)),"") -> 19200 | M851: =IF(L851="","",H851*L851) -> 19200 | N851: =IF(M851="","",J851-M851) -> 5300 | O851: =IFERROR(N851/J851,0) -> 0.21632653 | Q851: Ventas_Mayo_2026 - Ventas Mayo.csv | R851: - | S851: 82
A852: 46164 | B852: 2026 | C852: 5 | D852: Mayo | E852: Monterrey | F852: Luis Gómez | G852: Webcam HD | H852: 6 | I852: 1180 | J852: 7080 | K852: =H852*I852 -> 7080 | L852: =IFERROR(INDEX(Cat_Productos!$B$2:$B$6,MATCH(G852,Cat_Productos!$A$2:$A$6,0)),"") -> 590 | M852: =IF(L852="","",H852*L852) -> 3540 | N852: =IF(M852="","",J852-M852) -> 3540 | O852: =IFERROR(N852/J852,0) -> 0.5 | Q852: Ventas_Mayo_2026 - Ventas Mayo.csv | R852: - | S852: 18
A853: 46164 | B853: 2026 | C853: 5 | D853: Mayo | E853: Guadalajara | F853: Juan Pérez | G853: Monitor 27" | H853: 6 | I853: 6200 | J853: 37200 | K853: =H853*I853 -> 37200 | L853: =IFERROR(INDEX(Cat_Productos!$B$2:$B$6,MATCH(G853,Cat_Productos!$A$2:$A$6,0)),"") -> 4100 | M853: =IF(L853="","",H853*L853) -> 24600 | N853: =IF(M853="","",J853-M853) -> 12600 | O853: =IFERROR(N853/J853,0) -> 0.33870968 | Q853: Ventas_Mayo_2026 - Ventas Mayo.csv | R853: - | S853: 25 | T853: IMPORTE CALCULADO
A854: 46164 | B854: 2026 | C854: 5 | D854: Mayo | E854: CDMX | F854: María López | G854: Laptop Pro 14 | H854: 5 | I854: 24500 | J854: 122500 | K854: =H854*I854 -> 122500 | L854: =IFERROR(INDEX(Cat_Productos!$B$2:$B$6,MATCH(G854,Cat_Productos!$A$2:$A$6,0)),"") -> 19200 | M854: =IF(L854="","",H854*L854) -> 96000 | N854: =IF(M854="","",J854-M854) -> 26500 | O854: =IFERROR(N854/J854,0) -> 0.21632653 | Q854: Ventas_Mayo_2026 - Ventas Mayo.csv | R854: - | S854: 70 | T854: IMPORTE CALCULADO
A855: 46164 | B855: 2026 | C855: 5 | D855: Mayo | E855: Guadalajara | F855: Sofía Martínez | G855: Monitor 27" | H855: 3 | I855: 6200 | J855: 18600 | K855: =H855*I855 -> 18600 | L855: =IFERROR(INDEX(Cat_Productos!$B$2:$B$6,MATCH(G855,Cat_Productos!$A$2:$A$6,0)),"") -> 4100 | M855: =IF(L855="","",H855*L855) -> 12300 | N855: =IF(M855="","",J855-M855) -> 6300 | O855: =IFERROR(N855/J855,0) -> 0.33870968 | Q855: Ventas_Mayo_2026 - Ventas Mayo.csv | R855: - | S855: 10
A856: 46164 | B856: 2026 | C856: 5 | D856: Mayo | E856: Monterrey | F856: María López | G856: Teclado Mecánico | H856: 5 | I856: 1450 | J856: 7250 | K856: =H856*I856 -> 7250 | L856: =IFERROR(INDEX(Cat_Productos!$B$2:$B$6,MATCH(G856,Cat_Productos!$A$2:$A$6,0)),"") -> 780 | M856: =IF(L856="","",H856*L856) -> 3900 | N856: =IF(M856="","",J856-M856) -> 3350 | O856: =IFERROR(N856/J856,0) -> 0.46206897 | Q856: Ventas_Mayo_2026 - Ventas Mayo.csv | R856: - | S856: 56
A857: 46164 | B857: 2026 | C857: 5 | D857: Mayo | E857: Guadalajara | F857: Ana Torres | G857: Laptop Pro 14 | H857: 4 | I857: 24500 | J857: 98000 | K857: =H857*I857 -> 98000 | L857: =IFERROR(INDEX(Cat_Productos!$B$2:$B$6,MATCH(G857,Cat_Productos!$A$2:$A$6,0)),"") -> 19200 | M857: =IF(L857="","",H857*L857) -> 76800 | N857: =IF(M857="","",J857-M857) -> 21200 | O857: =IFERROR(N857/J857,0) -> 0.21632653 | Q857: Ventas_Mayo_2026 - Ventas Mayo.csv | R857: - | S857: 78
A858: 46165 | B858: 2026 | C858: 5 | D858: Mayo | E858: Monterrey | F858: María López | G858: Mouse Inalámbrico | H858: 4 | I858: 620 | J858: 2480 | K858: =H858*I858 -> 2480 | L858: =IFERROR(INDEX(Cat_Productos!$B$2:$B$6,MATCH(G858,Cat_Productos!$A$2:$A$6,0)),"") -> 290 | M858: =IF(L858="","",H858*L858) -> 1160 | N858: =IF(M858="","",J858-M858) -> 1320 | O858: =IFERROR(N858/J858,0) -> 0.53225806 | Q858: Ventas_Mayo_2026 - Ventas Mayo.csv | R858: - | S858: 95
A859: 46165 | B859: 2026 | C859: 5 | D859: Mayo | E859: CDMX | F859: Ana Torres | G859: Laptop Pro 14 | H859: 2 | I859: 24500 | J859: 49000 | K859: =H859*I859 -> 49000 | L859: =IFERROR(INDEX(Cat_Productos!$B$2:$B$6,MATCH(G859,Cat_Productos!$A$2:$A$6,0)),"") -> 19200 | M859: =IF(L859="","",H859*L859) -> 38400 | N859: =IF(M859="","",J859-M859) -> 10600 | O859: =IFERROR(N859/J859,0) -> 0.21632653 | Q859: Ventas_Mayo_2026 - Ventas Mayo.csv | R859: - | S859: 96
A860: 46165 | B860: 2026 | C860: 5 | D860: Mayo | E860: Monterrey | F860: Juan Pérez | G860: Monitor 27" | H860: 2 | I860: 6200 | J860: 12400 | K860: =H860*I860 -> 12400 | L860: =IFERROR(INDEX(Cat_Productos!$B$2:$B$6,MATCH(G860,Cat_Productos!$A$2:$A$6,0)),"") -> 4100 | M860: =IF(L860="","",H860*L860) -> 8200 | N860: =IF(M860="","",J860-M860) -> 4200 | O860: =IFERROR(N860/J860,0) -> 0.33870968 | Q860: Ventas_Mayo_2026 - Ventas Mayo.csv | R860: - | S860: 74
A861: 46165 | B861: 2026 | C861: 5 | D861: Mayo | E861: Monterrey | F861: María López | G861: Webcam HD | H861: 1 | I861: 1180 | J861: 1180 | K861: =H861*I861 -> 1180 | L861: =IFERROR(INDEX(Cat_Productos!$B$2:$B$6,MATCH(G861,Cat_Productos!$A$2:$A$6,0)),"") -> 590 | M861: =IF(L861="","",H861*L861) -> 590 | N861: =IF(M861="","",J861-M861) -> 590 | O861: =IFERROR(N861/J861,0) -> 0.5 | Q861: Ventas_Mayo_2026 - Ventas Mayo.csv | R861: - | S861: 8
A862: 46165 | B862: 2026 | C862: 5 | D862: Mayo | E862: CDMX | F862: Juan Pérez | G862: Webcam HD | H862: 4 | I862: 1180 | J862: 4720 | K862: =H862*I862 -> 4720 | L862: =IFERROR(INDEX(Cat_Productos!$B$2:$B$6,MATCH(G862,Cat_Productos!$A$2:$A$6,0)),"") -> 590 | M862: =IF(L862="","",H862*L862) -> 2360 | N862: =IF(M862="","",J862-M862) -> 2360 | O862: =IFERROR(N862/J862,0) -> 0.5 | Q862: Ventas_Mayo_2026 - Ventas Mayo.csv | R862: - | S862: 5
A863: 46165 | B863: 2026 | C863: 5 | D863: Mayo | E863: CDMX | F863: Juan Pérez | G863: Webcam HD | H863: 6 | I863: 1180 | J863: 7080 | K863: =H863*I863 -> 7080 | L863: =IFERROR(INDEX(Cat_Productos!$B$2:$B$6,MATCH(G863,Cat_Productos!$A$2:$A$6,0)),"") -> 590 | M863: =IF(L863="","",H863*L863) -> 3540 | N863: =IF(M863="","",J863-M863) -> 3540 | O863: =IFERROR(N863/J863,0) -> 0.5 | Q863: Ventas_Mayo_2026 - Ventas Mayo.csv | R863: - | S863: 4
...

Sheet Cobranza
A1: Fecha de corte: | B1: 46173 | C1: Supuesto: cierre del periodo analizado. Cambia esta celda y la antiguedad se recalcula
A3: Cliente | B3: Factura | C3: Mes | D3: Fecha_Emision | E3: Fecha_Vencimiento | F3: Monto | G3: Estatus | H3: Dias_Vencido | I3: Antiguedad | J3: Vendedor_Asignado | K3: Limite_Credito | L3: Dias_Credito
A4: Abarrotes La Esquina | B4: F-2600 | C4: Marzo | D4: 46094 | E4: 46109 | F4: 15200 | G4: Pagado | H4: =IF(G4="Pagado",0,IF(E4="","",MAX(0,$B$1-E4))) -> 0 | I4: =IF(G4="Pagado","Pagado",IF(E4="","Sin fecha de vencimiento",IF(H4<=0,"Por vencer",IF(H4<=30,"1 a 30 dias",IF(H4<=60,"31 a 60 dias",IF(H4<=90,"61 a 90 dias","Mas de 90 dias")))))) -> Pagado | J4: María López | K4: 40000 | L4: 7
A5: Abarrotes La Esquina | B5: F-2608 | C5: Marzo | D5: 46099 | E5: 46114 | F5: 33400 | G5: Pagado | H5: =IF(G5="Pagado",0,IF(E5="","",MAX(0,$B$1-E5))) -> 0 | I5: =IF(G5="Pagado","Pagado",IF(E5="","Sin fecha de vencimiento",IF(H5<=0,"Por vencer",IF(H5<=30,"1 a 30 dias",IF(H5<=60,"31 a 60 dias",IF(H5<=90,"61 a 90 dias","Mas de 90 dias")))))) -> Pagado | J5: María López | K5: 40000 | L5: 7
A6: Abarrotes La Esquina | B6: F-2619 | C6: Marzo | D6: 46101 | E6: 46116 | F6: 9800 | G6: Pagado | H6: =IF(G6="Pagado",0,IF(E6="","",MAX(0,$B$1-E6))) -> 0 | I6: =IF(G6="Pagado","Pagado",IF(E6="","Sin fecha de vencimiento",IF(H6<=0,"Por vencer",IF(H6<=30,"1 a 30 dias",IF(H6<=60,"31 a 60 dias",IF(H6<=90,"61 a 90 dias","Mas de 90 dias")))))) -> Pagado | J6: María López | K6: 40000 | L6: 7
A7: Grupo Salinas SA | B7: F-2616 | C7: Marzo | D7: 46090 | E7: 46120 | F7: 15200 | G7: Pagado | H7: =IF(G7="Pagado",0,IF(E7="","",MAX(0,$B$1-E7))) -> 0 | I7: =IF(G7="Pagado","Pagado",IF(E7="","Sin fecha de vencimiento",IF(H7<=0,"Por vencer",IF(H7<=30,"1 a 30 dias",IF(H7<=60,"31 a 60 dias",IF(H7<=90,"61 a 90 dias","Mas de 90 dias")))))) -> Pagado | J7: Juan Pérez | K7: 400000 | L7: 30
A8: Restaurante Don Pepe | B8: F-2612 | C8: Abril | D8: 46123 | E8: 46153 | F8: 5600 | G8: Pagado | H8: =IF(G8="Pagado",0,IF(E8="","",MAX(0,$B$1-E8))) -> 0 | I8: =IF(G8="Pagado","Pagado",IF(E8="","Sin fecha de vencimiento",IF(H8<=0,"Por vencer",IF(H8<=30,"1 a 30 dias",IF(H8<=60,"31 a 60 dias",IF(H8<=90,"61 a 90 dias","Mas de 90 dias")))))) -> Pagado | J8: Carlos Ruiz | K8: 60000 | L8: 15
A9: Abarrotes La Esquina | B9: F-2601 | C9: Mayo | D9: 46144 | E9: 46174 | F9: 73500 | G9: Pagado | H9: =IF(G9="Pagado",0,IF(E9="","",MAX(0,$B$1-E9))) -> 0 | I9: =IF(G9="Pagado","Pagado",IF(E9="","Sin fecha de vencimiento",IF(H9<=0,"Por vencer",IF(H9<=30,"1 a 30 dias",IF(H9<=60,"31 a 60 dias",IF(H9<=90,"61 a 90 dias","Mas de 90 dias")))))) -> Pagado | J9: María López | K9: 40000 | L9: 7
A10: Abarrotes La Esquina | B10: F-2623 | C10: Mayo | D10: 46155 | E10: 46185 | F10: 42000 | G10: Pagado | H10: =IF(G10="Pagado",0,IF(E10="","",MAX(0,$B$1-E10))) -> 0 | I10: =IF(G10="Pagado","Pagado",IF(E10="","Sin fecha de vencimiento",IF(H10<=0,"Por vencer",IF(H10<=30,"1 a 30 dias",IF(H10<=60,"31 a 60 dias",IF(H10<=90,"61 a 90 dias","Mas de 90 dias")))))) -> Pagado | J10: María López | K10: 40000 | L10: 7
A11: Abarrotes La Esquina | B11: F-2401 | C11: Enero | F11: 42000 | G11: Pagado | H11: =IF(G11="Pagado",0,IF(E11="","",MAX(0,$B$1-E11))) -> 0 | I11: =IF(G11="Pagado","Pagado",IF(E11="","Sin fecha de vencimiento",IF(H11<=0,"Por vencer",IF(H11<=30,"1 a 30 dias",IF(H11<=60,"31 a 60 dias",IF(H11<=90,"61 a 90 dias","Mas de 90 dias")))))) -> Pagado | J11: María López | K11: 40000 | L11: 7
A12: Abarrotes La Esquina | B12: F-2400 | C12: Enero | F12: 56000 | G12: Pagado | H12: =IF(G12="Pagado",0,IF(E12="","",MAX(0,$B$1-E12))) -> 0 | I12: =IF(G12="Pagado","Pagado",IF(E12="","Sin fecha de vencimiento",IF(H12<=0,"Por vencer",IF(H12<=30,"1 a 30 dias",IF(H12<=60,"31 a 60 dias",IF(H12<=90,"61 a 90 dias","Mas de 90 dias")))))) -> Pagado | J12: María López | K12: 40000 | L12: 7
A13: Grupo Salinas SA | B13: F-2426 | C13: Marzo | F13: 56000 | G13: Pagado | H13: =IF(G13="Pagado",0,IF(E13="","",MAX(0,$B$1-E13))) -> 0 | I13: =IF(G13="Pagado","Pagado",IF(E13="","Sin fecha de vencimiento",IF(H13<=0,"Por vencer",IF(H13<=30,"1 a 30 dias",IF(H13<=60,"31 a 60 dias",IF(H13<=90,"61 a 90 dias","Mas de 90 dias")))))) -> Pagado | J13: Juan Pérez | K13: 400000 | L13: 30
A14: Comercial El Roble | B14: F-2425 | C14: Marzo | F14: 9800 | G14: Pagado | H14: =IF(G14="Pagado",0,IF(E14="","",MAX(0,$B$1-E14))) -> 0 | I14: =IF(G14="Pagado","Pagado",IF(E14="","Sin fecha de vencimiento",IF(H14<=0,"Por vencer",IF(H14<=30,"1 a 30 dias",IF(H14<=60,"31 a 60 dias",IF(H14<=90,"61 a 90 dias","Mas de 90 dias")))))) -> Pagado | J14: Ana Torres | K14: 80000 | L14: 30
A15: Clinica Santa Fe | B15: F-2402 | C15: Enero | F15: 128000 | G15: Pagado | H15: =IF(G15="Pagado",0,IF(E15="","",MAX(0,$B$1-E15))) -> 0 | I15: =IF(G15="Pagado","Pagado",IF(E15="","Sin fecha de vencimiento",IF(H15<=0,"Por vencer",IF(H15<=30,"1 a 30 dias",IF(H15<=60,"31 a 60 dias",IF(H15<=90,"61 a 90 dias","Mas de 90 dias")))))) -> Pagado | J15: María López | K15: 120000 | L15: 45
A16: Restaurante Don Pepe | B16: F-2403 | C16: Enero | F16: 21000 | G16: Pagado | H16: =IF(G16="Pagado",0,IF(E16="","",MAX(0,$B$1-E16))) -> 0 | I16: =IF(G16="Pagado","Pagado",IF(E16="","Sin fecha de vencimiento",IF(H16<=0,"Por vencer",IF(H16<=30,"1 a 30 dias",IF(H16<=60,"31 a 60 dias",IF(H16<=90,"61 a 90 dias","Mas de 90 dias")))))) -> Pagado | J16: Carlos Ruiz | K16: 60000 | L16: 15
A17: Clinica Santa Fe | B17: F-2405 | C17: Enero | F17: 21000 | G17: Pagado | H17: =IF(G17="Pagado",0,IF(E17="","",MAX(0,$B$1-E17))) -> 0 | I17: =IF(G17="Pagado","Pagado",IF(E17="","Sin fecha de vencimiento",IF(H17<=0,"Por vencer",IF(H17<=30,"1 a 30 dias",IF(H17<=60,"31 a 60 dias",IF(H17<=90,"61 a 90 dias","Mas de 90 dias")))))) -> Pagado | J17: María López | K17: 120000 | L17: 45
A18: Óptica Visión | B18: F-2408 | C18: Enero | F18: 33400 | G18: Pagado | H18: =IF(G18="Pagado",0,IF(E18="","",MAX(0,$B$1-E18))) -> 0 | I18: =IF(G18="Pagado","Pagado",IF(E18="","Sin fecha de vencimiento",IF(H18<=0,"Por vencer",IF(H18<=30,"1 a 30 dias",IF(H18<=60,"31 a 60 dias",IF(H18<=90,"61 a 90 dias","Mas de 90 dias")))))) -> Pagado | J18: Sofía Martínez | K18: 45000 | L18: 15
A19: Autopartes Norte | B19: F-2409 | C19: Enero | F19: 5600 | G19: Pagado | H19: =IF(G19="Pagado",0,IF(E19="","",MAX(0,$B$1-E19))) -> 0 | I19: =IF(G19="Pagado","Pagado",IF(E19="","Sin fecha de vencimiento",IF(H19<=0,"Por vencer",IF(H19<=30,"1 a 30 dias",IF(H19<=60,"31 a 60 dias",IF(H19<=90,"61 a 90 dias","Mas de 90 dias")))))) -> Pagado | J19: Sofía Martínez | K19: 100000 | L19: 15
A20: Óptica Visión | B20: F-2410 | C20: Febrero | F20: 42000 | G20: Pagado | H20: =IF(G20="Pagado",0,IF(E20="","",MAX(0,$B$1-E20))) -> 0 | I20: =IF(G20="Pagado","Pagado",IF(E20="","Sin fecha de vencimiento",IF(H20<=0,"Por vencer",IF(H20<=30,"1 a 30 dias",IF(H20<=60,"31 a 60 dias",IF(H20<=90,"61 a 90 dias","Mas de 90 dias")))))) -> Pagado | J20: Sofía Martínez | K20: 45000 | L20: 15
A21: Comercial El Roble | B21: F-2411 | C21: Febrero | F21: 8500 | G21: Pagado | H21: =IF(G21="Pagado",0,IF(E21="","",MAX(0,$B$1-E21))) -> 0 | I21: =IF(G21="Pagado","Pagado",IF(E21="","Sin fecha de vencimiento",IF(H21<=0,"Por vencer",IF(H21<=30,"1 a 30 dias",IF(H21<=60,"31 a 60 dias",IF(H21<=90,"61 a 90 dias","Mas de 90 dias")))))) -> Pagado | J21: Ana Torres | K21: 80000 | L21: 30
A22: Papeleria Central | B22: F-2414 | C22: Febrero | F22: 5600 | G22: Pagado | H22: =IF(G22="Pagado",0,IF(E22="","",MAX(0,$B$1-E22))) -> 0 | I22: =IF(G22="Pagado","Pagado",IF(E22="","Sin fecha de vencimiento",IF(H22<=0,"Por vencer",IF(H22<=30,"1 a 30 dias",IF(H22<=60,"31 a 60 dias",IF(H22<=90,"61 a 90 dias","Mas de 90 dias")))))) -> Pagado | J22: Ana Torres | K22: 90000 | L22: 30
... A32: Grupo Salinas SA | B32: F-2427 | C32: Marzo | F32: 5600 | G32: Pagado | H32: =IF(G32="Pagado",0,IF(E32="","",MAX(0,$B$1-E32))) -> 0 | I32: =IF(G32="Pagado","Pagado",IF(E32="","Sin fecha de vencimiento",IF(H32<=0,"Por vencer",IF(H32<=30,"1 a 30 dias",IF(H32<=60,"31 a 60 dias",IF(H32<=90,"61 a 90 dias","Mas de 90 dias")))))) -> Pagado | J32: Juan Pérez | K32: 400000 | L32: 30
A33: Distribuidora Andrade | B33: F-2605 | C33: Marzo | D33: 46083 | E33: 46113 | F33: 42000 | G33: Pendiente | H33: =IF(G33="Pagado",0,IF(E33="","",MAX(0,$B$1-E33))) -> 60 | I33: =IF(G33="Pagado","Pagado",IF(E33="","Sin fecha de vencimiento",IF(H33<=0,"Por vencer",IF(H33<=30,"1 a 30 dias",IF(H33<=60,"31 a 60 dias",IF(H33<=90,"61 a 90 dias","Mas de 90 dias")))))) -> 31 a 60 dias | J33: Juan Pérez | K33: 150000 | L33: 30
A34: Constructora Vega | B34: F-2606 | C34: Marzo | D34: 46099 | E34: 46114 | F34: 33400 | G34: Pendiente | H34: =IF(G34="Pagado",0,IF(E34="","",MAX(0,$B$1-E34))) -> 59 | I34: =IF(G34="Pagado","Pagado",IF(E34="","Sin fecha de vencimiento",IF(H34<=0,"Por vencer",IF(H34<=30,"1 a 30 dias",IF(H34<=60,"31 a 60 dias",IF(H34<=90,"61 a 90 dias","Mas de 90 dias")))))) -> 31 a 60 dias | J34: Luis Gómez | K34: 200000 | L34: 45
A35: Clinica Santa Fe | B35: F-2609 | C35: Marzo | D35: 46097 | E35: 46117 | F35: 73500 | G35: Pendiente | H35: =IF(G35="Pagado",0,IF(E35="","",MAX(0,$B$1-E35))) -> 56 | I35: =IF(G35="Pagado","Pagado",IF(E35="","Sin fecha de vencimiento",IF(H35<=0,"Por vencer",IF(H35<=30,"1 a 30 dias",IF(H35<=60,"31 a 60 dias",IF(H35<=90,"61 a 90 dias","Mas de 90 dias")))))) -> 31 a 60 dias | J35: María López | K35: 120000 | L35: 45
A36: Papeleria Central | B36: F-2621 | C36: Marzo | D36: 46087 | E36: 46117 | F36: 21000 | G36: Pendiente | H36: =IF(G36="Pagado",0,IF(E36="","",MAX(0,$B$1-E36))) -> 56 | I36: =IF(G36="Pagado","Pagado",IF(E36="","Sin fecha de vencimiento",IF(H36<=0,"Por vencer",IF(H36<=30,"1 a 30 dias",IF(H36<=60,"31 a 60 dias",IF(H36<=90,"61 a 90 dias","Mas de 90 dias")))))) -> 31 a 60 dias | J36: Ana Torres | K36: 90000 | L36: 30
A37: Comercial El Roble | B37: F-2624 | C37: Marzo | D37: 46089 | E37: 46119 | F37: 8500 | G37: Pendiente | H37: =IF(G37="Pagado",0,IF(E37="","",MAX(0,$B$1-E37))) -> 54 | I37: =IF(G37="Pagado","Pagado",IF(E37="","Sin fecha de vencimiento",IF(H37<=0,"Por vencer",IF(H37<=30,"1 a 30 dias",IF(H37<=60,"31 a 60 dias",IF(H37<=90,"61 a 90 dias","Mas de 90 dias")))))) -> 31 a 60 dias | J37: Ana Torres | K37: 80000 | L37: 30
A38: Grupo Salinas SA | B38: F-2602 | C38: Abril | D38: 46126 | E38: 46132 | F38: 128000 | G38: Pendiente | H38: =IF(G38="Pagado",0,IF(E38="","",MAX(0,$B$1-E38))) -> 41 | I38: =IF(G38="Pagado","Pagado",IF(E38="","Sin fecha de vencimiento",IF(H38<=0,"Por vencer",IF(H38<=30,"1 a 30 dias",IF(H38<=60,"31 a 60 dias",IF(H38<=90,"61 a 90 dias","Mas de 90 dias")))))) -> 31 a 60 dias | J38: Juan Pérez | K38: 400000 | L38: 30
A39: Clinica Santa Fe | B39: F-2625 | C39: Marzo | D39: 46090 | E39: 46135 | F39: 8500 | G39: Pendiente | H39: =IF(G39="Pagado",0,IF(E39="","",MAX(0,$B$1-E39))) -> 38 | I39: =IF(G39="Pagado","Pagado",IF(E39="","Sin fecha de vencimiento",IF(H39<=0,"Por vencer",IF(H39<=30,"1 a 30 dias",IF(H39<=60,"31 a 60 dias",IF(H39<=90,"61 a 90 dias","Mas de 90 dias")))))) -> 31 a 60 dias | J39: María López | K39: 120000 | L39: 45
A40: Restaurante Don Pepe | B40: F-2603 | C40: Abril | D40: 46114 | E40: 46144 | F40: 15200 | G40: Pendiente | H40: =IF(G40="Pagado",0,IF(E40="","",MAX(0,$B$1-E40))) -> 29 | I40: =IF(G40="Pagado","Pagado",IF(E40="","Sin fecha de vencimiento",IF(H40<=0,"Por vencer",IF(H40<=30,"1 a 30 dias",IF(H40<=60,"31 a 60 dias",IF(H40<=90,"61 a 90 dias","Mas de 90 dias")))))) -> 1 a 30 dias | J40: Carlos Ruiz | K40: 60000 | L40: 15
A41: Papeleria Central | B41: F-2614 | C41: Abril | D41: 46114 | E41: 46152 | F41: 56000 | G41: Pendiente | H41: =IF(G41="Pagado",0,IF(E41="","",MAX(0,$B$1-E41))) -> 21 | I41: =IF(G41="Pagado","Pagado",IF(E41="","Sin fecha de vencimiento",IF(H41<=0,"Por vencer",IF(H41<=30,"1 a 30 dias",IF(H41<=60,"31 a 60 dias",IF(H41<=90,"61 a 90 dias","Mas de 90 dias")))))) -> 1 a 30 dias | J41: Ana Torres | K41: 90000 | L41: 30
A42: Restaurante Don Pepe | B42: F-2607 | C42: Mayo | D42: 46148 | E42: 46163 | F42: 33400 | G42: Pendiente | H42: =IF(G42="Pagado",0,IF(E42="","",MAX(0,$B$1-E42))) -> 10 | I42: =IF(G42="Pagado","Pagado",IF(E42="","Sin fecha de vencimiento",IF(H42<=0,"Por vencer",IF(H42<=30,"1 a 30 dias",IF(H42<=60,"31 a 60 dias",IF(H42<=90,"61 a 90 dias","Mas de 90 dias")))))) -> 1 a 30 dias | J42: Carlos Ruiz | K42: 60000 | L42: 15
A43: Comercial El Roble | B43: F-2622 | C43: Abril | D43: 46140 | E43: 46170 | F43: 5600 | G43: Pendiente | H43: =IF(G43="Pagado",0,IF(E43="","",MAX(0,$B$1-E43))) -> 3 | I43: =IF(G43="Pagado","Pagado",IF(E43="","Sin fecha de vencimiento",IF(H43<=0,"Por vencer",IF(H43<=30,"1 a 30 dias",IF(H43<=60,"31 a 60 dias",IF(H43<=90,"61 a 90 dias","Mas de 90 dias")))))) -> 1 a 30 dias | J43: Ana Torres | K43: 80000 | L43: 30
A44: Autopartes Norte | B44: F-2604 | C44: Mayo | D44: 46161 | E44: 46176 | F44: 33400 | G44: Pendiente | H44: =IF(G44="Pagado",0,IF(E44="","",MAX(0,$B$1-E44))) -> 0 | I44: =IF(G44="Pagado","Pagado",IF(E44="","Sin fecha de vencimiento",IF(H44<=0,"Por vencer",IF(H44<=30,"1 a 30 dias",IF(H44<=60,"31 a 60 dias",IF(H44<=90,"61 a 90 dias","Mas de 90 dias")))))) -> Por vencer | J44: Sofía Martínez | K44: 100000 | L44: 15
... A50: Papeleria Central | B50: F-2610 | C50: Mayo | D50: 46157 | E50: 46202 | F50: 5600 | G50: Pendiente | H50: =IF(G50="Pagado",0,IF(E50="","",MAX(0,$B$1-E50))) -> 0 | I50: =IF(G50="Pagado","Pagado",IF(E50="","Sin fecha de vencimiento",IF(H50<=0,"Por vencer",IF(H50<=30,"1 a 30 dias",IF(H50<=60,"31 a 60 dias",IF(H50<=90,"61 a 90 dias","Mas de 90 dias")))))) -> Por vencer | J50: Ana Torres | K50: 90000 | L50: 30
A51: Hotel Miramar | B51: F-2404 | C51: Enero | F51: 56000 | G51: Pendiente | H51: =IF(G51="Pagado",0,IF(E51="","",MAX(0,$B$1-E51))) | I51: =IF(G51="Pagado","Pagado",IF(E51="","Sin fecha de vencimiento",IF(H51<=0,"Por vencer",IF(H51<=30,"1 a 30 dias",IF(H51<=60,"31 a 60 dias",IF(H51<=90,"61 a 90 dias","Mas de 90 dias")))))) -> Sin fecha de vencimiento | J51: Carlos Ruiz | K51: 180000 | L51: 30
A52: Abarrotes La Esquina | B52: F-2406 | C52: Enero | F52: 33400 | G52: Pendiente | H52: =IF(G52="Pagado",0,IF(E52="","",MAX(0,$B$1-E52))) | I52: =IF(G52="Pagado","Pagado",IF(E52="","Sin fecha de vencimiento",IF(H52<=0,"Por vencer",IF(H52<=30,"1 a 30 dias",IF(H52<=60,"31 a 60 dias",IF(H52<=90,"61 a 90 dias","Mas de 90 dias")))))) -> Sin fecha de vencimiento | J52: María López | K52: 40000 | L52: 7
A53: Comercial El Roble | B53: F-2407 | C53: Enero | F53: 5600 | G53: Pendiente | H53: =IF(G53="Pagado",0,IF(E53="","",MAX(0,$B$1-E53))) | I53: =IF(G53="Pagado","Pagado",IF(E53="","Sin fecha de vencimiento",IF(H53<=0,"Por vencer",IF(H53<=30,"1 a 30 dias",IF(H53<=60,"31 a 60 dias",IF(H53<=90,"61 a 90 dias","Mas de 90 dias")))))) -> Sin fecha de vencimiento | J53: Ana Torres | K53: 80000 | L53: 30
A54: Constructora Vega | B54: F-2412 | C54: Febrero | F54: 5600 | G54: Pendiente | H54: =IF(G54="Pagado",0,IF(E54="","",MAX(0,$B$1-E54))) | I54: =IF(G54="Pagado","Pagado",IF(E54="","Sin fecha de vencimiento",IF(H54<=0,"Por vencer",IF(H54<=30,"1 a 30 dias",IF(H54<=60,"31 a 60 dias",IF(H54<=90,"61 a 90 dias","Mas de 90 dias")))))) -> Sin fecha de vencimiento | J54: Luis Gómez | K54: 200000 | L54: 45
A55: Grupo Salinas SA | B55: F-2413 | C55: Febrero | F55: 56000 | G55: Pendiente | H55: =IF(G55="Pagado",0,IF(E55="","",MAX(0,$B$1-E55))) | I55: =IF(G55="Pagado","Pagado",IF(E55="","Sin fecha de vencimiento",IF(H55<=0,"Por vencer",IF(H55<=30,"1 a 30 dias",IF(H55<=60,"31 a 60 dias",IF(H55<=90,"61 a 90 dias","Mas de 90 dias")))))) -> Sin fecha de vencimiento | J55: Juan Pérez | K55: 400000 | L55: 30
A56: Constructora Vega | B56: F-2423 | C56: Marzo | F56: 9800 | G56: Pendiente | H56: =IF(G56="Pagado",0,IF(E56="","",MAX(0,$B$1-E56))) | I56: =IF(G56="Pagado","Pagado",IF(E56="","Sin fecha de vencimiento",IF(H56<=0,"Por vencer",IF(H56<=30,"1 a 30 dias",IF(H56<=60,"31 a 60 dias",IF(H56<=90,"61 a 90 dias","Mas de 90 dias")))))) -> Sin fecha de vencimiento | J56: Luis Gómez | K56: 200000 | L56: 45
A57: Ferreteria Lopez | B57: F-2620 | C57: Abril | D57: 46117 | E57: 46147 | F57: 21000 | H57: =IF(G57="Pagado",0,IF(E57="","",MAX(0,$B$1-E57))) -> 26 | I57: =IF(G57="Pagado","Pagado",IF(E57="","Sin fecha de vencimiento",IF(H57<=0,"Por vencer",IF(H57<=30,"1 a 30 dias",IF(H57<=60,"31 a 60 dias",IF(H57<=90,"61 a 90 dias","Mas de 90 dias")))))) -> 1 a 30 dias | J57: Juan Pérez | K57: 70000 | L57: 30

Sheet Validacion
A1: VALIDACION CONTRA LOS REPORTES PREVIOS
A2: Se compara el maestro contra los archivos ya procesados que existian en la carpeta. Ninguna diferencia queda sin explicar.
A3: Concepto | B3: Fuente_previa | C3: Valor_previo | D3: Valor_maestro | E3: Diferencia | F3: % | G3: Explicacion
A4: Ventas Mayo 2026 | B4: Reporte_Ventas_Mayo_2026_LIMPIO.xlsx (hoja Ventas) | C4: 2848860 | D4: 2848860 | E4: 0 | F4: 0 | G4: Cuadra al peso con el reporte depurado. Contra el registro comercial faltan 4,720 de Juan Perez, hueco que el cruce del 14-jul ya reportaba
A5: Ventas Mayo por vendedor (detalle) | B5: Cruce_Ventas_Cobranza_Mayo_2026.xlsx | C5: 2848860 | D5: 2848860 | E5: 0 | F5: 0 | G5: Cuadra al peso con el cruce previo una vez que se excluye su fila de totales
A6: Ventas Enero 2026 | B6: Metas_Comisiones_2026.xlsx (Ventas Ene) | C6: 2109960 | D6: 2137680 | E6: 27720 | F6: 0.01313769 | G6: +23,900 de una operacion de Maria Lopez que solo existe en el XLSX de enero, mas +3,820 de dos importes capturados que no cuadran con cantidad x precio
A7: Ventas Febrero 2026 | B7: Metas_Comisiones_2026.xlsx (Ventas Feb) | C7: 2415260 | D7: 2415260 | E7: 0 | F7: 0 | G7: Sin diferencia
A8: Ventas Marzo 2026 | B8: Metas_Comisiones_2026.xlsx (Ventas Mar) | C8: 2774760 | D8: 2750260 | E8: -24500 | F8: -0.0088295925 | G8: -24,500 exactamente: la operacion marcada DEVOLUCION que el maestro conserva en positivo y el registro comercial ya habia restado
A9: Ventas Abril 2026 | B9: Metas_Comisiones_2026.xlsx (Ventas Abr) | C9: 3083330 | D9: 3083330 | E9: 0 | F9: 0 | G9: Sin diferencia
A10: Ventas Mayo 2026 | B10: Metas_Comisiones_2026.xlsx (Ventas May) | C10: 2853580 | D10: 2848860 | E10: -4720 | F10: -0.0016540626 | G10: Cuadra al peso con el reporte depurado. Contra el registro comercial faltan 4,720 de Juan Perez, hueco que el cruce del 14-jul ya reportaba

Sheet Excepciones
A1: EXCEPCIONES Y PENDIENTES
A2: Ordenadas por impacto en pesos. Lo que esta hasta arriba es lo que hay que resolver primero.
A3: Tipo | B3: Archivo | C3: Hoja | D3: Fila | E3: Detalle | F3: Impacto_MXN
A4: Diferencia vs reporte previo | B4: Cruce_Ventas_Cobranza_Mayo_2026.xlsx | C4: - | D4: - | E4: Ventas Mayo por vendedor (detalle): maestro 2,848,860 vs previo 5,697,720 (-50.0%) | F4: -2848860
A5: Diferencia vs reporte previo | B5: Cruce_Ventas_Cobranza_Mayo_2026.xlsx | C5: - | D5: - | E5: Ventas Mayo por vendedor (detalle): maestro 2,848,860 vs previo 5,697,720 (-50.0%) | F5: -2848860
A6: Cobranza sin fecha | B6: Cobranza_Q1_2026.xlsx | C6: cxc Q1 | D6: - | E6: 6 facturas pendientes del Q1 no traen fecha de vencimiento; no se pueden clasificar por antiguedad | F6: 166400
A7: Cobranza sin fecha | B7: Cobranza_Q1_2026.xlsx | C7: cxc Q1 | D7: - | E7: 6 facturas pendientes del Q1 no traen fecha de vencimiento; no se pueden clasificar por antiguedad | F7: 166400
A8: Cobranza sin fecha | B8: Cobranza_Q1_2026.xlsx | C8: cxc Q1 | D8: - | E8: 6 facturas pendientes del Q1 no traen fecha de vencimiento; no se pueden clasificar por antiguedad | F8: 166400
A9: Diferencia vs reporte previo | B9: Metas_Comisiones_2026.xlsx (Ventas Ene) | C9: - | D9: - | E9: Ventas Enero 2026: maestro 2,137,680 vs previo 2,109,960 (+1.3%) | F9: 27720
A10: Diferencia vs reporte previo | B10: Metas_Comisiones_2026.xlsx (Ventas Ene) | C10: - | D10: - | E10: Ventas Enero 2026: maestro 2,137,680 vs previo 2,109,960 (+1.3%) | F10: 27720
A11: Diferencia vs reporte previo | B11: Metas_Comisiones_2026.xlsx (Ventas Ene) | C11: - | D11: - | E11: Ventas Enero 2026: maestro 2,137,680 vs previo 2,109,960 (+1.3%) | F11: 27720
A12: Diferencia vs reporte previo | B12: Metas_Comisiones_2026.xlsx (Ventas Mar) | C12: - | D12: - | E12: Ventas Marzo 2026: maestro 2,750,260 vs previo 2,774,760 (-0.9%) | F12: -24500
A13: Devolucion | B13: marzo_ventas.csv | C13: - | D13: 225 | E13: Marcada como DEVOLUCION en el origen. Se conserva en positivo, pendiente decidir si se resta | F13: -24500
A14: Diferencia vs reporte previo | B14: Metas_Comisiones_2026.xlsx (Ventas Mar) | C14: - | D14: - | E14: Ventas Marzo 2026: maestro 2,750,260 vs previo 2,774,760 (-0.9%) | F14: -24500
A15: Diferencia vs reporte previo | B15: Metas_Comisiones_2026.xlsx (Ventas Mar) | C15: - | D15: - | E15: Ventas Marzo 2026: maestro 2,750,260 vs previo 2,774,760 (-0.9%) | F15: -24500
A16: Importe inconsistente | B16: ventas enero FINAL FINAL.xlsx | C16: enero | D16: 5 | E16: Importe capturado 28,900 vs cantidad x precio 23,900 | F16: 5000
A17: Precio fuera de lista | B17: Lista_Precios_2026.xlsx | C17: precios | D17: - | E17: Abril: Monitor 27" se facturo a 6,200 y la lista dice 6,300 (13 operaciones) | F17: -4600
A18: Precio fuera de lista | B18: Lista_Precios_2026.xlsx | C18: precios | D18: - | E18: Abril: Monitor 27" se facturo a 6,200 y la lista dice 6,300 (13 operaciones) | F18: -4600
A19: Precio fuera de lista | B19: Lista_Precios_2026.xlsx | C19: precios | D19: - | E19: Abril: Monitor 27" se facturo a 6,200 y la lista dice 6,300 (13 operaciones) | F19: -4600
A20: Importe inconsistente | B20: ventas enero FINAL FINAL.xlsx | C20: enero | D20: 9 | E20: Importe capturado 4,620 vs cantidad x precio 5,800 | F20: -1180
A21: Posible duplicado | B21: marzo_ventas.csv | C21: - | D21: - | E21: 2 filas identicas: 2026-03-23 Sofía Martínez Mouse Inalámbrico x4. Se conservan todas, puede ser venta legitima repetida
A22: Posible duplicado | B22: Ventas_Abril_FINAL_v2.xlsx | C22: - | D22: - | E22: 2 filas identicas: 2026-04-09 Carlos Ruiz Teclado Mecánico x2. Se conservan todas, puede ser venta legitima repetida
A23: Posible duplicado | B23: Ventas_Abril_FINAL_v2.xlsx | C23: - | D23: - | E23: 2 filas identicas: 2026-04-09 Ana Torres Teclado Mecánico x6. Se conservan todas, puede ser venta legitima repetida
A24: Posible duplicado | B24: Ventas_Abril_FINAL_v2.xlsx | C24: - | D24: - | E24: 2 filas identicas: 2026-04-09 Ana Torres Teclado Mecánico x4. Se conservan todas, puede ser venta legitima repetida
A25: Posible duplicado | B25: Ventas_Abril_FINAL_v2.xlsx | C25: - | D25: - | E25: 2 filas identicas: 2026-04-08 Sofía Martínez Webcam HD x3. Se conservan todas, puede ser venta legitima repetida
A26: Posible duplicado | B26: Ventas_Abril_FINAL_v2.xlsx | C26: - | D26: - | E26: 2 filas identicas: 2026-04-07 Luis Gómez Teclado Mecánico x4. Se conservan todas, puede ser venta legitima repetida
A27: Posible duplicado | B27: Ventas_Abril_FINAL_v2.xlsx | C27: - | D27: - | E27: 2 filas identicas: 2026-04-05 Ana Torres Teclado Mecánico x4. Se conservan todas, puede ser venta legitima repetida
A28: Posible duplicado | B28: Ventas_Abril_FINAL_v2.xlsx | C28: - | D28: - | E28: 2 filas identicas: 2026-04-05 Ana Torres Teclado Mecánico x2. Se conservan todas, puede ser venta legitima repetida
A29: Posible duplicado | B29: Ventas_Abril_FINAL_v2.xlsx | C29: - | D29: - | E29: 2 filas identicas: 2026-04-01 Luis Gómez Teclado Mecánico x2. Se conservan todas, puede ser venta legitima repetida
A30: Posible duplicado | B30: marzo_ventas.csv | C30: - | D30: - | E30: 2 filas identicas: 2026-03-25 María López Teclado Mecánico x2. Se conservan todas, puede ser venta legitima repetida
A31: Posible duplicado | B31: marzo_ventas.csv | C31: - | D31: - | E31: 2 filas identicas: 2026-03-25 Ana Torres Teclado Mecánico x6. Se conservan todas, puede ser venta legitima repetida
A32: Posible duplicado | B32: ventas enero FINAL FINAL.xlsx | C32: - | D32: - | E32: 3 filas identicas: 2026-01-03 María López Teclado Mecánico x4. Se conservan todas, puede ser venta legitima repetida
... A47: Posible duplicado | B47: marzo_ventas.csv | C47: - | D47: - | E47: 2 filas identicas: 2026-03-09 Juan Pérez Mouse Inalámbrico x2. Se conservan todas, puede ser venta legitima repetida
A48: Fecha ilegible | B48: Ventas Febrero 26.xlsx | C48: Hoja1 | D48: 92 | E48: No se pudo interpretar la fecha 'nan'; la fila se excluye del maestro
A49: Fecha ilegible | B49: Ventas Febrero 26.xlsx | C49: Hoja1 | D49: 93 | E49: No se pudo interpretar la fecha 'nan'; la fila se excluye del maestro
A50: Fecha ilegible | B50: marzo_ventas.csv | C50: - | D50: 226 | E50: No se pudo interpretar la fecha 'nan'; la fila se excluye del maestro
A51: Nota del capturista | B51: Ventas_Abril_FINAL_v2.xlsx | C51: NOTAS | D51: - | E51: - Faltan capturas del 28 al 30 de abril (Ana salió de viaje).
A52: Nota del capturista | B52: Ventas_Abril_FINAL_v2.xlsx | C52: NOTAS | D52: - | E52: - Los precios de laptop ya subieron desde marzo, verificar lista.
A53: Nota del capturista | B53: Ventas_Abril_FINAL_v2.xlsx | C53: NOTAS | D53: - | E53: - Luis todavía se está integrando, lleva pocas ventas.
A54: Fecha ilegible | B54: Ventas_Mayo_2026 - Ventas Mayo.csv | C54: - | D54: 36 | E54: No se pudo interpretar la fecha 'nan'; la fila se excluye del maestro
A55: Fecha ilegible | B55: Ventas_Mayo_2026 - Ventas Mayo.csv | C55: - | D55: 91 | E55: No se pudo interpretar la fecha 'nan'; la fila se excluye del maestro
A56: Posible duplicado | B56: ventas enero FINAL FINAL.xlsx | C56: - | D56: - | E56: 2 filas identicas: 2026-01-01 Carlos Ruiz Mouse Inalámbrico x2. Se conservan todas, puede ser venta legitima repetida
A57: Posible duplicado | B57: ventas enero FINAL FINAL.xlsx | C57: - | D57: - | E57: 2 filas identicas: 2026-01-03 Ana Torres Teclado Mecánico x2. Se conservan todas, puede ser venta legitima repetida
A58: Posible duplicado | B58: Ventas_Abril_FINAL_v2.xlsx | C58: - | D58: - | E58: 2 filas identicas: 2026-04-27 Ana Torres Mouse Inalámbrico x2. Se conservan todas, puede ser venta legitima repetida
A59: Posible duplicado | B59: Ventas_Abril_FINAL_v2.xlsx | C59: - | D59: - | E59: 2 filas identicas: 2026-04-26 Juan Pérez Webcam HD x3. Se conservan todas, puede ser venta legitima repetida
A60: Posible duplicado | B60: Ventas_Abril_FINAL_v2.xlsx | C60: - | D60: - | E60: 2 filas identicas: 2026-04-23 Carlos Ruiz Mouse Inalámbrico x2. Se conservan todas, puede ser venta legitima repetida
A61: Posible duplicado | B61: Ventas_Abril_FINAL_v2.xlsx | C61: - | D61: - | E61: 2 filas identicas: 2026-04-23 Luis Gómez Mouse Inalámbrico x6. Se conservan todas, puede ser venta legitima repetida
A62: Posible duplicado | B62: Ventas_Abril_FINAL_v2.xlsx | C62: - | D62: - | E62: 2 filas identicas: 2026-04-21 María López Teclado Mecánico x2. Se conservan todas, puede ser venta legitima repetida
A63: Posible duplicado | B63: Ventas_Abril_FINAL_v2.xlsx | C63: - | D63: - | E63: 2 filas identicas: 2026-04-20 Juan Pérez Laptop Pro 14 x5. Se conservan todas, puede ser venta legitima repetida
A64: Posible duplicado | B64: Ventas_Abril_FINAL_v2.xlsx | C64: - | D64: - | E64: 2 filas identicas: 2026-04-19 Carlos Ruiz Mouse Inalámbrico x4. Se conservan todas, puede ser venta legitima repetida
A65: Posible duplicado | B65: Ventas_Abril_FINAL_v2.xlsx | C65: - | D65: - | E65: 2 filas identicas: 2026-04-19 Ana Torres Teclado Mecánico x4. Se conservan todas, puede ser venta legitima repetida
A66: Posible duplicado | B66: Ventas_Abril_FINAL_v2.xlsx | C66: - | D66: - | E66: 2 filas identicas: 2026-04-19 Ana Torres Teclado Mecánico x2. Se conservan todas, puede ser venta legitima repetida
A67: Posible duplicado | B67: Ventas_Abril_FINAL_v2.xlsx | C67: - | D67: - | E67: 2 filas identicas: 2026-04-18 Sofía Martínez Monitor 27" x5. Se conservan todas, puede ser venta legitima repetida
... A122: Posible duplicado | B122: marzo_ventas.csv | C122: - | D122: - | E122: 2 filas identicas: 2026-03-01 Ana Torres Mouse Inalámbrico x6. Se conservan todas, puede ser venta legitima repetida

Sheet Conciliacion
A1: BITACORA DE CONCILIACION
A2: Cada decision tomada sobre los datos, con el archivo de origen.
A3: Fase | B3: Archivo | C3: Hoja | D3: Fila | E3: Accion | F3: Detalle
A4: Lectura | B4: Ventas_Enero_2026.csv | C4: - | D4: - | E4: Encoding | F4: Archivo no es UTF-8, se leyo como Latin-1
A5: Duplicados | B5: Ventas_Enero_2026.csv / ventas enero FINAL FINAL.xlsx | C5: - | D5: - | E5: Dos versiones del mismo mes | F5: CSV 180 filas, XLSX 181 filas. Coinciden 180 operaciones. Se toma el XLSX como primario (mas reciente y con importes completos); se recuperan del CSV las filas que no estan en el XLSX: 0
A6: Duplicados | B6: ventas enero FINAL FINAL.xlsx | C6: enero | D6: - | E6: Solo en primario | F6: 1 operaciones existen solo en el XLSX
A7: Encabezados | B7: Ventas Febrero 26.xlsx | C7: Hoja1 | D7: 1-2 | E7: Encabezado desplazado | F7: El encabezado real estaba en la fila 3 (arriba habia titulo)
A8: Ruido | B8: marzo_ventas.csv | C8: - | D8: 227 | E8: Fila descartada | F8: Fila de nota dentro de los datos: 'OJO: faltan 2 ventas de Luis por capturar'
A9: Estructura | B9: Ventas_Abril_FINAL_v2.xlsx | C9: CDMX | D9: - | E9: Hoja por sucursal | F9: Se apilo la hoja y se asigno Sucursal = CDMX a partir del nombre de la hoja
A10: Estructura | B10: Ventas_Abril_FINAL_v2.xlsx | C10: GDL | D10: - | E10: Hoja por sucursal | F10: Se apilo la hoja y se asigno Sucursal = GDL a partir del nombre de la hoja
A11: Estructura | B11: Ventas_Abril_FINAL_v2.xlsx | C11: MTY | D11: - | E11: Hoja por sucursal | F11: Se apilo la hoja y se asigno Sucursal = MTY a partir del nombre de la hoja
A12: Importes | B12: Ventas_Mayo_2026 - Ventas Mayo.csv | C12: - | D12: 9 | E12: Importe calculado | F12: Importe vacio, se calculo 3.0 x 1,450
A13: Importes | B13: Ventas_Mayo_2026 - Ventas Mayo.csv | C13: - | D13: 25 | E13: Importe calculado | F13: Importe vacio, se calculo 6.0 x 6,200
A14: Importes | B14: Ventas_Mayo_2026 - Ventas Mayo.csv | C14: - | D14: 44 | E14: Importe calculado | F14: Importe vacio, se calculo 6.0 x 6,200
A15: Ruido | B15: Ventas_Mayo_2026 - Ventas Mayo.csv | C15: - | D15: 64 | E15: Fila descartada | F15: Fila de subtotal 'TOTAL PARCIAL' dentro de los datos
A16: Importes | B16: Ventas_Mayo_2026 - Ventas Mayo.csv | C16: - | D16: 70 | E16: Importe calculado | F16: Importe vacio, se calculo 5.0 x 24,500
A17: Importes | B17: Ventas_Mayo_2026 - Ventas Mayo.csv | C17: - | D17: 94 | E17: Importe calculado | F17: Importe vacio, se calculo 5.0 x 1,180
A18: Importes | B18: Ventas_Mayo_2026 - Ventas Mayo.csv | C18: - | D18: 108 | E18: Importe calculado | F18: Importe vacio, se calculo 4.0 x 6,200
A19: Catalogos | B19: Costos_Productos.csv | C19: - | D19: - | E19: Nombre de producto homologado | F19: 'laptop pro 14' en el catalogo de costos se ligo con 'Laptop Pro 14' del maestro. Sin esto el margen de ese producto salia al 100%
A20: Catalogos | B20: Costos_Productos.csv | C20: - | D20: - | E20: Nombre de producto homologado | F20: 'MONITOR 27' en el catalogo de costos se ligo con 'Monitor 27"' del maestro. Sin esto el margen de ese producto salia al 100%
A21: Catalogos | B21: Costos_Productos.csv | C21: - | D21: - | E21: Nombre de producto homologado | F21: 'Teclado Mec.' en el catalogo de costos se ligo con 'Teclado Mecánico' del maestro. Sin esto el margen de ese producto salia al 100%
A22: Catalogos | B22: Costos_Productos.csv | C22: - | D22: - | E22: Nombre de producto homologado | F22: 'webcam hd' en el catalogo de costos se ligo con 'Webcam HD' del maestro. Sin esto el margen de ese producto salia al 100%
A23: Catalogos | B23: Costos_Productos.csv | C23: - | D23: - | E23: Nombre de producto homologado | F23: 'Mouse Inalambrico' en el catalogo de costos se ligo con 'Mouse Inalámbrico' del maestro. Sin esto el margen de ese producto salia al 100%
A24: Catalogos | B24: Costos_Productos.csv | C24: - | D24: - | E24: Nombre de producto homologado | F24: 'laptop pro 14' en el catalogo de costos se ligo con 'Laptop Pro 14' del maestro. Sin esto el margen de ese producto salia al 100%
A25: Catalogos | B25: Costos_Productos.csv | C25: - | D25: - | E25: Nombre de producto homologado | F25: 'MONITOR 27' en el catalogo de costos se ligo con 'Monitor 27"' del maestro. Sin esto el margen de ese producto salia al 100%
A26: Catalogos | B26: Costos_Productos.csv | C26: - | D26: - | E26: Nombre de producto homologado | F26: 'Teclado Mec.' en el catalogo de costos se ligo con 'Teclado Mecánico' del maestro. Sin esto el margen de ese producto salia al 100%
A27: Catalogos | B27: Costos_Productos.csv | C27: - | D27: - | E27: Nombre de producto homologado | F27: 'webcam hd' en el catalogo de costos se ligo con 'Webcam HD' del maestro. Sin esto el margen de ese producto salia al 100%
A28: Catalogos | B28: Costos_Productos.csv | C28: - | D28: - | E28: Nombre de producto homologado | F28: 'Mouse Inalambrico' en el catalogo de costos se ligo con 'Mouse Inalámbrico' del maestro. Sin esto el margen de ese producto salia al 100%

Sheet Diccionario
A1: DICCIONARIO DE EQUIVALENCIAS
A2: Cada variante de nombre encontrada en los archivos y el valor canonico al que se agrupo. Corrige aqui si algo quedo mal agrupado.
A3: Campo | B3: Valor_original | C3: Valor_canonico | D3: Metodo | E3: Confianza
A4: Sucursal | B4: GDL | C4: Guadalajara | D4: diccionario | E4: Alta
A5: Vendedor | B5: JUAN PEREZ | C5: Juan Pérez | D5: diccionario | E5: Alta
A6: Sucursal | B6: MTY | C6: Monterrey | D6: diccionario | E6: Alta
A7: Vendedor | B7: SOFIA MARTINEZ | C7: Sofía Martínez | D7: diccionario | E7: Alta
A8: Vendedor | B8: MARIA LOPEZ | C8: María López | D8: diccionario | E8: Alta
A9: Vendedor | B9: ANA TORRES | C9: Ana Torres | D9: diccionario | E9: Alta
A10: Vendedor | B10: CARLOS RUIZ | C10: Carlos Ruiz | D10: diccionario | E10: Alta
A11: Sucursal | B11: Gdl | C11: Guadalajara | D11: diccionario | E11: Alta
A12: Vendedor | B12: juan pérez | C12: Juan Pérez | D12: diccionario | E12: Alta
A13: Vendedor | B13: JUAN PÉREZ | C13: Juan Pérez | D13: diccionario | E13: Alta
A14: Sucursal | B14: Mty | C14: Monterrey | D14: diccionario | E14: Alta
... A56: Producto | B56: laptop pro14 | C56: Laptop Pro 14 | D56: diccionario | E56: Alta

Sheet Cat_Productos
A1: Producto | B1: Costo_Unitario | C1: Proveedor | D1: Precio_Enero | E1: Precio_Febrero | F1: Precio_Marzo | G1: Precio_Abril | H1: Precio_Mayo | I1: Notas
A2: Laptop Pro 14 | B2: 19200 | C2: Mayorista TecnoImport | D2: 23900 | E2: 23900 | F2: 24500 | G2: 24500 | H2: 24500 | I2: Subió en marzo por tipo de cambio
A3: Monitor 27" | B3: 4100 | C3: Mayorista TecnoImport | D3: 5900 | E3: 5900 | F3: 6200 | G3: 6300 | H3: 6200 | I3: OJO: abril se facturó a 6200, no 6300
A4: Mouse Inalámbrico | B4: 290 | C4: Perifericos MX | D4: 620 | E4: 620 | F4: 620 | G4: 620 | H4: 620
A5: Teclado Mecánico | B5: 780 | C5: Perifericos MX | D5: 1450 | E5: 1450 | F5: 1450 | G5: 1450 | H5: 1450
A6: Webcam HD | B6: 590 | C6: Perifericos MX | D6: 1180 | E6: 1180 | F6: 1180 | G6: 1180 | H6: 1180

Sheet Cat_Vendedores
A1: Vendedor | B1: Sucursal | C1: Meta_Mensual | D1: Pct_Comision | E1: Ventas_Ene_registro | F1: Ventas_Feb_registro | G1: Ventas_Mar_registro | H1: Ventas_Abr_registro | I1: Ventas_May_registro
A2: Ana Torres | B2: CDMX | C2: 220000 | D2: 0.025 | E2: 589900 | F2: 680030 | G2: 720050 | H2: 776720 | I2: 466010
A3: Carlos Ruiz | B3: Monterrey | C3: 280000 | D3: 0.045 | E3: 210250 | F3: 225250 | G3: 235050 | H3: 243540 | I3: 242980
A4: Juan Pérez | B4: Guadalajara | C4: 250000 | D4: 0.03 | E4: 520160 | F4: 609860 | G4: 689890 | H4: 758320 | I4: 711150
A5: Luis Gómez | B5: Guadalajara | C5: 260000 | D5: 0.035 | G5: 150160 | H5: 232750 | I5: 384260
A6: María López | B6: CDMX | C6: 300000 | D6: 0.05 | E6: 379980 | F6: 429840 | G6: 470100 | H6: 507020 | I6: 516740
A7: Sofía Martínez | B7: Monterrey | C7: 200000 | D7: 0.06 | E7: 409670 | F7: 470280 | G7: 509510 | H7: 564980 | I7: 532440

Sheet Cat_Gastos
A1: Sucursal | B1: Mes | C1: Renta | D1: Nomina | E1: Servicios | F1: Otros | G1: Total_Gasto
A2: CDMX | B2: Enero | C2: 45000 | D2: 182000 | E2: 23310 | F2: 6153 | G2: =SUM(C2:F2) -> 256463
A3: CDMX | B3: Febrero | C3: 45000 | D3: 179775 | E3: 23171 | F3: 15685 | G3: =SUM(C3:F3) -> 263631
A4: CDMX | B4: Marzo | C4: 45000 | D4: 189342 | E4: 24529 | F4: 6581 | G4: =SUM(C4:F4) -> 265452
A5: CDMX | B5: Abril | C5: 45000 | D5: 202472 | E5: 24779 | F5: 8824 | G5: =SUM(C5:F5) -> 281075
A6: CDMX | B6: Mayo | C6: 45000 | D6: 198872 | E6: 24683 | F6: 10856 | G6: =SUM(C6:F6) -> 279411
A7: Guadalajara | B7: Enero | C7: 38000 | D7: 151000 | E7: 17844 | F7: 8124 | G7: =SUM(C7:F7) -> 214968
A8: Guadalajara | B8: Febrero | C8: 38000 | D8: 148373 | E8: 19768 | F8: 16874 | G8: =SUM(C8:F8) -> 223015
A9: Guadalajara | B9: Marzo | C9: 38000 | D9: 147350 | E9: 18649 | F9: 6168 | G9: =SUM(C9:F9) -> 210167
A10: Guadalajara | B10: Abril | C10: 38000 | D10: 143071 | E10: 19444 | F10: 6171 | G10: =SUM(C10:F10) -> 206686
A11: Guadalajara | B11: Mayo | C11: 38000 | D11: 171860 | E11: 20179 | F11: 12192 | G11: =SUM(C11:F11) -> 242231
A12: Monterrey | B12: Enero | C12: 32000 | D12: 124000 | E12: 14914 | F12: 16137 | G12: =SUM(C12:F12) -> 187051
A13: Monterrey | B13: Febrero | C13: 32000 | D13: 131874 | E13: 15221 | F13: 15887 | G13: =SUM(C13:F13) -> 194982
... A16: Monterrey | B16: Mayo | C16: 32000 | D16: 116196 | E16: 17515 | F16: 12088 | G16: =SUM(C16:F16) -> 177799

Sheet Cat_Clientes
A1: Cliente | B1: Zona | C1: Vendedor asignado | D1: Contacto | E1: Teléfono | F1: Límite crédito | G1: Días crédito
A2: Clinica Santa Fe | B2: CDMX | C2: María López | D2: Laura Fentanes | E2: 55-1234-5601 | F2: 120000 | G2: 45
A3: Grupo Salinas SA | B3: GDL | C3: Juan Pérez | D3: Roberto Salinas | E3: 33-2345-6702 | F3: 400000 | G3: 30
A4: Papeleria Central | B4: CDMX | C4: Ana Torres | D4: Miguel Ángel Ruiz | E4: 55-3456-7803 | F4: 90000 | G4: 30
A5: Restaurante Don Pepe | B5: MTY | C5: Carlos Ruiz | D5: José Pérez | E5: 81-4567-8904 | F5: 60000 | G5: 15
A6: Distribuidora Andrade | B6: GDL | C6: Juan Pérez | D6: Sandra Andrade | E6: 33-5678-9005 | F6: 150000 | G6: 30
A7: Constructora Vega | B7: GDL | C7: Luis Gómez | D7: Iván Vega | E7: 33-6789-0106 | F7: 200000 | G7: 45
A8: Autopartes Norte | B8: MTY | C8: Sofía Martínez | D8: Hugo Cantú | E8: 81-7890-1207 | F8: 100000 | G8: 15
A9: Comercial El Roble | B9: CDMX | C9: Ana Torres | D9: Patricia Roble | E9: 55-8901-2308 | F9: 80000 | G9: 30
A10: Boutique Aurora | B10: MTY | C10: Sofía Martínez | D10: Aurora Méndez | E10: 81-9012-3409 | F10: 50000 | G10: 45
A11: Abarrotes La Esquina | B11: CDMX | C11: María López | D11: Don Chucho | E11: 55-0123-4510 | F11: 40000 | G11: 7
A12: Ferreteria Lopez | B12: GDL | C12: Juan Pérez | D12: Ramón López | E12: 33-1234-5611 | F12: 70000 | G12: 30
A13: Hotel Miramar | B13: MTY | C13: Carlos Ruiz | D13: Gabriela Sосa | E13: 81-2345-6712 | F13: 180000 | G13: 30
... A16: Óptica Visión | B16: MTY | C16: Sofía Martínez | D16: Claudia Ibarra | E16: 81-5678-9015 | F16: 45000 | G16: 15
